Workbook

Sheet FÓRMULAS
A2: VENDA | B2: SAÍDA
A3: DOAÇÃO | B3: SAÍDA
A4: ENTRADA | B4: ENTRADA
A5: DEVOLUÇÃO | B5: ENTRADA
A7: PIX | B7: -
A8: PIX | B8: 0
A9: DÉBITO | B9: *1,90%
A10: CRÉDITO
A11: CRÉDITO 2X

Sheet ITENS
B1: PRODUTOS PARA VENDA
B2: CÓDIGO | C2: DESCRIÇÃO | D2: VLR ÚLTIMA COMPRA | E2: OBS
B3: 2470 | C3: CAMISA CHAMPIONS | D3: 109.9
B4: 2550 | C4: BONE LUXO | D4: 29
B5: 2731 | C5: BONÉ BRIM | D5: 29
B6: 2827 | C6: ETQ. LETRA PRINT FIX | D6: 0.57
B7: 2828 | C7: ETQ. NÚMERO PRINT FIX | D7: 4.28
B8: 2946 | C8: MASCOTE PORTO VITÓRIA | D8: 62.5
B9: 2953 | C9: COPO TÉRMICO TULIP 500ML | D9: 150
B10: 2957 | C10: GARRAFA TÉRMICA 660 ML | D10: 180
B11: 2959 | C11: CANECA PORTO | D11: 15
B12: 3006 | C12: REGATA BASQUETE | D12: =79.92+10 -> 89.92 | E12: Considerando R$10,00 de aplicação de detalhes
B13: 3007 | C13: CAMISA POLO | D13: =119.9+10 -> 129.9 | E13: Considerando R$10,00 de aplicação de detalhes
B14: 3008 | C14: CAMISA OFICIAL | D14: =119.9+10 -> 129.9 | E14: Considerando R$10,00 de aplicação de detalhes
B15: 3009 | C15: BERMUDA | D15: =79.9 -> 79.9
B16: 3010 | C16: JAQUETA TORCEDOR | D16: =149.9+10 -> 159.9 | E16: Considerando R$10,00 de aplicação de detalhes
B17: 3049 | C17: CAMISA ESPECIAL RETRÔ | D17: 129.9

Sheet MOVIMENTO
B1: - Portal de Vendas
B2: Alíquota SN | C2: 0.04
B3: CÓD. PRODUTO | C3: DESCRIÇÃO PRODUTO | D3: DESCRIÇÃO TOP | E3: QTD | F3: MOVIMENTO | G3: DT NEGOCIAÇÃO | H3: DIA DA SEMANA | I3: CÓD. PARCEIRO / DESCRIÇÃO | J3: NF | K3: VLR BRUTO | L3: DESCONTOS | M3: TOTAL | N3: TRIBUTOS | O3: TX CARTÃO | P3: MODALIDADE | Q3: BANDEIRA | R3: VLR LÍQUIDO | S3: VLR UN. LÍQUIDO | T3: ENTRADA EXTRATO | U3: VLR EXTRATO | V3: OBS
B4: 2470 | C4: CAMISA CHAMPIONS | D4: VENDA | E4: 1 | F4: SAÍDA | G4: 45845 | H4: - | I4: 3433 - CONSUMIDOR FINAL | J4: 1019 | K4: 180 | L4: 0 | M4: =K4-L4 -> 180 | N4: =M4*C2 -> 7.2 | O4: =M4*1.9% -> 3.42 | P4: DÉBITO | Q4: VISA | R4: =M4-N4-O4 -> 169.38 | S4: =R4/E4 -> 169.38 | T4: JULHO | U4: =M4-O4 -> 176.58 | V4: Venda ocorreu dia 05/07/25
B5: 2550 | C5: BONÉ LUXO | D5: VENDA | E5: 2 | F5: SAÍDA | G5: 45845 | H5: - | I5: 3433 - CONSUMIDOR FINAL | J5: 1020 | K5: 120 | L5: 0 | M5: =K5-L5 -> 120 | N5: =M5*C2 -> 4.8 | O5: 0 | P5: PIX | Q5: - | R5: =M5-N5-O5 -> 115.2 | S5: =R5/E5 -> 57.6 | T5: JUNHO | U5: =M5-O5 -> 120 | V5: Venda ocorreu dia 09/06/25
B6: 2470 | C6: CAMISA CHAMPIONS | D6: VENDA | E6: 1 | F6: SAÍDA | G6: 45845 | H6: - | I6: 3433 - CONSUMIDOR FINAL | J6: 1021 | K6: 180 | L6: 80 | M6: =K6-L6 -> 100 | N6: =M6*C2 -> 4 | O6: =M6*1.9% -> 1.9 | P6: DÉBITO | Q6: VISA | R6: =M6-N6-O6 -> 94.1 | S6: =R6/E6 -> 94.1 | T6: JUNHO | U6: =M6-O6 -> 98.1 | V6: Venda ocorreu dia 14/06 pelo Lindeyr
B7: 2470 | C7: CAMISA CHAMPIONS | D7: VENDA | E7: 1 | F7: SAÍDA | G7: 45845 | H7: - | I7: 3433 - CONSUMIDOR FINAL | J7: 1022 | K7: 180 | L7: 80 | M7: =K7-L7 -> 100 | N7: =M7*C2 -> 4 | O7: =M7*1.9% -> 1.9 | P7: DÉBITO | Q7: MASTERCARD | R7: =M7-N7-O7 -> 94.1 | S7: =R7/E7 -> 94.1 | T7: JUNHO | U7: =M7-O7 -> 98.1 | V7: Venda ocorreu dia 14/06 pelo Lindeyr
B8: 2470 | C8: CAMISA CHAMPIONS | D8: VENDA | E8: 1 | F8: SAÍDA | G8: 45845 | H8: - | I8: 3433 - CONSUMIDOR FINAL | J8: 1023 | K8: 180 | L8: 80 | M8: =K8-L8 -> 100 | N8: =M8*C2 -> 4 | O8: 0 | P8: PIX | Q8: - | R8: =M8-N8-O8 -> 96 | S8: =R8/E8 -> 96 | T8: JUNHO | U8: =M8-O8 -> 100 | V8: Venda ocorreu dia 14/06 pelo Lindeyr
B9: 2470 | C9: CAMISA CHAMPIONS | D9: VENDA | E9: 1 | F9: SAÍDA | G9: 45845 | H9: - | I9: 3433 - CONSUMIDOR FINAL | J9: 1024 | K9: 180 | L9: 0 | M9: =K9-L9 -> 180 | N9: =M9*C2 -> 7.2 | O9: 0 | P9: PIX | Q9: - | R9: =M9-N9-O9 -> 172.8 | S9: =R9/E9 -> 172.8 | T9: JUNHO | U9: =M9-O9 -> 180 | V9: Venda ocorreu dia 14/06 pelo Lindeyr
B10: 2470 | C10: CAMISA CHAMPIONS | D10: VENDA | E10: 1 | F10: SAÍDA | G10: 45845 | H10: - | I10: 3433 - CONSUMIDOR FINAL | J10: 1024 | K10: 180 | L10: 80 | M10: =K10-L10 -> 100 | N10: =M10*C2 -> 4 | O10: 0 | P10: PIX | Q10: - | R10: =M10-N10-O10 -> 96 | S10: =R10/E10 -> 96 | T10: JUNHO | U10: =M10-O10 -> 100 | V10: Venda ocorreu dia 14/06 pelo Lindeyr
B11: 2470 | C11: CAMISA CHAMPIONS | D11: VENDA | E11: 1 | F11: SAÍDA | G11: 45846 | H11: - | I11: 3433 - CONSUMIDOR FINAL | J11: 1025 | K11: 180 | L11: 0 | M11: =K11-L11 -> 180 | N11: =M11*C2 -> 7.2 | O11: 0 | P11: PIX | Q11: - | R11: =M11-N11-O11 -> 172.8 | S11: =R11/E11 -> 172.8 | T11: JUNHO | U11: =M11-O11 -> 180 | V11: Venda ocorreu em junho
B12: 2470 | C12: CAMISA CHAMPIONS | D12: VENDA | E12: 1 | F12: SAÍDA | G12: 45846 | H12: - | I12: 3433 - CONSUMIDOR FINAL | J12: 1026 | K12: 180 | L12: 0 | M12: =K12-L12 -> 180 | N12: =M12*C2 -> 7.2 | O12: =M12*1.9% -> 3.42 | P12: DÉBITO | Q12: VISA | R12: =M12-N12-O12 -> 169.38 | S12: =R12/E12 -> 169.38 | T12: JUNHO | U12: =M12-O12 -> 176.58 | V12: Venda ocorreu em junho
B13: 2550 | C13: BONÉ LUXO | D13: VENDA | E13: 1 | F13: SAÍDA | G13: 45846 | H13: TERÇA | I13: 3433 - CONSUMIDOR FINAL | J13: 1027 | K13: 60 | L13: 0 | M13: =K13-L13 -> 60 | N13: =M13*C2 -> 2.4 | O13: 0 | P13: PIX | Q13: - | R13: =M13-N13-O13 -> 57.6 | S13: 0 | T13: JUNHO | U13: =M13-O13 -> 60 | V13: USADA PARA UM RECEBIMENTO DO DIA 13/06 QUE NÃO FOI EMITIDO NF
B14: 3008 | C14: CAMISA OFICIAL | D14: VENDA | E14: 1 | F14: SAÍDA | G14: 45846 | H14: TERÇA | I14: 3433 - CONSUMIDOR FINAL | J14: 1028 | K14: 215 | L14: 43 | M14: =K14-L14 -> 172 | N14: =M14*C2 -> 6.88 | O14: =M14*2.71% -> 4.6612 | P14: CRÉDITO | Q14: MASTERCARD | R14: =M14-N14-O14 -> 160.4588 | S14: =R14/E14 -> 160.4588 | T14: AGOSTO | U14: =M14-O14 -> 167.3388 | V14: Plataforma Stone
B15: 2470 | C15: CAMISA CHAMPIONS | D15: VENDA | E15: 1 | F15: SAÍDA | G15: 45846 | H15: TERÇA | I15: 3433 - CONSUMIDOR FINAL | J15: 1029 | K15: 180 | L15: 0 | M15: =K15-L15 -> 180 | N15: =M15*C2 -> 7.2 | O15: =M15*0.75% -> 1.35 | P15: PIX | Q15: - | R15: =M15-N15-O15 -> 171.45 | S15: =R15/E15 -> 171.45 | T15: JULHO | U15: =M15-O15 -> 178.65 | V15: Plataforma Stone
B16: 2470 | C16: CAMISA CHAMPIONS | D16: VENDA | E16: 3 | F16: SAÍDA | G16: 45847 | H16: QUARTA | I16: 3433 - CONSUMIDOR FINAL | J16: 1030 | K16: 540 | L16: 108 | M16: =K16-L16 -> 432 | N16: =M16*C2 -> 17.28 | O16: =M16*2.9% -> 12.528 | P16: CRÉDITO 4X | Q16: VISA | R16: =M16-N16-O16 -> 402.192 | S16: =R16/E16 -> 134.064 | T16: AGOSTO | U16: =M16/4-O16/4 -> 104.868 | V16: Plataforma Stone
T17: SETEMBRO | U17: =U16 -> 104.868
T18: OUTUBRO | U18: =U17 -> 104.868
T19: NOVEMBRO | U19: =U18 -> 104.868
B20: 2550 | C20: BONÉ LUXO | D20: VENDA | E20: 1 | F20: SAÍDA | G20: 45847 | H20: QUARTA | I20: 3433 - CONSUMIDOR FINAL | J20: 1030 | K20: 60 | L20: 12 | M20: =K20-L20 -> 48 | N20: =M20*C2 -> 1.92 | O20: =M20*2.9% -> 1.392 | P20: CRÉDITO 4X | Q20: VISA | R20: =M20-N20-O20 -> 44.688 | S20: =R20/E20 -> 44.688 | T20: AGOSTO | U20: =M20/4-O20/4 -> 11.652 | V20: Plataforma Stone
T21: SETEMBRO | U21: =U20 -> 11.652
T22: OUTUBRO | U22: =U21 -> 11.652
T23: NOVEMBRO | U23: =U22 -> 11.652
B24: 3010 | C24: JAQUETA TORCEDOR | D24: VENDA | E24: 1 | F24: SAÍDA | G24: 45847 | H24: QUARTA | I24: 3433 - CONSUMIDOR FINAL | J24: 1031 | K24: 250 | L24: 0 | M24: =K24-L24 -> 250 | N24: =M24*C2 -> 10 | O24: =M24*2.9% -> 7.25 | P24: CRÉDITO 2X | Q24: MASTERCARD | R24: =M24-N24-O24 -> 232.75 | S24: =M24/E20 -> 250 | T24: AGOSTO | U24: =M24/2-O24/2 -> 121.375 | V24: Plataforma Stone
T25: SETEMBRO | U25: =U24 -> 121.375
B26: 3008 | C26: CAMISA OFICIAL | D26: VENDA | E26: 1 | F26: SAÍDA | G26: 45847 | H26: QUARTA | I26: 3433 - CONSUMIDOR FINAL | J26: 1031 | K26: 215 | L26: 0 | M26: =K26-L26 -> 215 | N26: =M26*C2 -> 8.6 | O26: =M26*2.9% -> 6.235 | P26: CRÉDITO 2X | Q26: MASTERCARD | R26: =M26-N26-O26 -> 200.165 | S26: =M26/E26 -> 215 | T26: AGOSTO | U26: =M26/2-O26/2 -> 104.3825 | V26: Plataforma Stone
T27: SETEMBRO | U27: =U26 -> 104.3825
B28: 3007 | C28: CAMISA POLO | D28: VENDA | E28: 1 | F28: SAÍDA | G28: 45847 | H28: QUARTA | I28: 3433 - CONSUMIDOR FINAL | J28: 1031 | K28: 200 | L28: 0 | M28: =K28-L28 -> 200 | N28: =M28*C2 -> 8 | O28: =M28*2.9% -> 5.8 | P28: CRÉDITO 2X | Q28: MASTERCARD | R28: =M28-N28-O28 -> 186.2 | S28: =M28/E28 -> 200 | T28: AGOSTO | U28: =M28/2-O28/2 -> 97.1 | V28: Plataforma Stone
T29: SETEMBRO | U29: =U28 -> 97.1
B30: 3008 | C30: CAMISA OFICIAL | D30: VENDA | E30: 2 | F30: SAÍDA | G30: 45848 | H30: QUINTA | I30: 2908 - MARCELO BRANDÃO | J30: 1032 | K30: 430 | L30: 86 | M30: =K30-L30 -> 344 | N30: =M30*C2 -> 13.76 | O30: =M30*2.9% -> 9.976 | P30: CRÉDITO 2X | Q30: MASTERCARD | R30: =M30-N30-O30 -> 320.264 | S30: =M30/E30 -> 172 | T30: AGOSTO | U30: =M30/2-O30/2 -> 167.012 | V30: Plataforma Stone
T31: SETEMBRO | U31: =U30 -> 167.012
B32: 2470 | C32: CAMISA CHAMPIONS | D32: VENDA | E32: 1 | F32: SAÍDA | G32: 45849 | H32: SEXTA | I32: 3433 - CONSUMIDOR FINAL | J32: 1033 | K32: 180 | L32: 0 | M32: =K32-L32 -> 180 | N32: =M32*C2 -> 7.2 | O32: =M32*2.71% -> 4.878 | P32: CRÉDITO | Q32: MASTERCARD | R32: =M32-N32-O32 -> 167.922 | S32: =R32/E32 -> 167.922 | T32: AGOSTO | U32: =M32-O32 -> 175.122 | V32: Plataforma Stone
B33: 2470 | C33: CAMISA CHAMPIONS | D33: VENDA | E33: 1 | F33: SAÍDA | G33: 45850 | H33: SÁBADO | I33: 3433 - CONSUMIDOR FINAL | J33: 1034 | K33: 180 | L33: 0 | M33: =K33-L33 -> 180 | N33: =M33*C2 -> 7.2 | O33: =M33*3.78% -> 6.804 | P33: CRÉDITO 2X | Q33: VISA | R33: =M33-N33-O33 -> 165.996 | S33: =R33/E33 -> 165.996 | T33: AGOSTO | U33: =M33/2-O33/2 -> 86.598
T34: SETEMBRO | U34: =U33 -> 86.598
B35: 2550 | C35: BONÉ LUXO | D35: VENDA | E35: 1 | F35: SAÍDA | G35: 45850 | H35: SÁBADO | I35: 3433 - CONSUMIDOR FINAL | J35: 1035 | K35: 60 | L35: 0 | M35: =K35-L35 -> 60 | N35: =M35*C2 -> 2.4 | O35: =M35*3.29% -> 1.974 | P35: CRÉDITO | Q35: VISA | R35: =M35-N35-O35 -> 55.626 | S35: =R35/E35 -> 55.626 | T35: AGOSTO | U35: =M35-O35 -> 58.026
B36: 3006 | C36: REGATA BASQUETE | D36: VENDA | E36: 1 | F36: SAÍDA | G36: 45850 | H36: SÁBADO | I36: 3433 - CONSUMIDOR FINAL | J36: 1036 | K36: 170 | L36: 0 | M36: =K36-L36 -> 170 | N36: =M36*C2 -> 6.8 | O36: 1.27 | P36: PIX | Q36: - | R36: =M36-N36-O36 -> 161.93 | S36: =R36/E36 -> 161.93 | T36: JULHO | U36: =M36-O36 -> 168.73 | V36: Plataforma Stone
B37: 2470 | C37: CAMISA CHAMPIONS | D37: VENDA | E37: 1 | F37: SAÍDA | G37: 45850 | H37: SÁBADO | I37: 3433 - CONSUMIDOR FINAL | J37: 1037 | K37: 180 | L37: 0 | M37: =K37-L37 -> 180 | N37: =M37*C2 -> 7.2 | O37: =M37*2.9% -> 5.22 | P37: CRÉDITO 2X | Q37: VISA | R37: =M37-N37-O37 -> 167.58 | S37: =R37/E37 -> 167.58 | T37: AGOSTO | U37: =M37/2-O37/2 -> 87.39 | V37: Plataforma Stone
T38: SETEMBRO | U38: =U37 -> 87.39
B39: 2731 | C39: BONÉ BRIM | D39: VENDA | E39: 1 | F39: SAÍDA | G39: 45850 | H39: SÁBADO | I39: 3433 - CONSUMIDOR FINAL | J39: 1037 | K39: 60 | L39: 0 | M39: =K39-L39 -> 60 | N39: =M39*C2 -> 2.4 | O39: =M39*2.9% -> 1.74 | P39: CRÉDITO 2X | Q39: VISA | R39: =M39-N39-O39 -> 55.86 | S39: =R39/E39 -> 55.86 | T39: AGOSTO | U39: =M39/2-O39/2 -> 29.13 | V39: Plataforma Stone
T40: SETEMBRO | U40: =U39 -> 29.13
B41: 3010 | C41: JAQUETA TORCEDOR | D41: VENDA | E41: 1 | F41: SAÍDA | G41: 45851 | H41: SEGUNDA | I41: 3433 - CONSUMIDOR FINAL | J41: 1038 | K41: 250 | L41: 0 | M41: =K41-L41 -> 250 | N41: =M41*C2 -> 10 | O41: =M41*2.9% -> 7.25 | P41: CRÉDITO 2X | Q41: MASTERCARD | R41: =M41-N41-O41 -> 232.75 | S41: =R41/E41 -> 232.75 | T41: AGOSTO | U41: =M41/2-O41/2 -> 121.375 | V41: Plataforma Stone
T42: SETEMBRO | U42: =U41 -> 121.375
B43: 2470 | C43: CAMISA CHAMPIONS | D43: VENDA | E43: 1 | F43: SAÍDA | G43: 45851 | H43: SEGUNDA | I43: 3433 - CONSUMIDOR FINAL | J43: 1039 | K43: 180 | L43: 0 | M43: =K43-L43 -> 180 | N43: =M43*C2 -> 7.2 | O43: =M43*3.78% -> 6.804 | P43: CRÉDITO 2X | Q43: VISA | R43: =M43-N43-O43 -> 165.996 | S43: =R43/E43 -> 165.996 | T43: AGOSTO | U43: =M43/2-O43/2 -> 86.598 | V43: PLATAFORMA STONE
T44: SETEMBRO | U44: =U43 -> 86.598
B45: 2470 | C45: CAMISA CHAMPIONS | D45: VENDA | E45: 1 | F45: SAÍDA | G45: 45853 | H45: TERÇA | I45: 3433 - CONSUMIDOR FINAL | J45: 1041 | K45: 180 | L45: 0 | M45: =K45-L45 -> 180 | N45: =M45*C2 -> 7.2 | O45: =M45*2.9% -> 5.22 | P45: CRÉDITO 2X | Q45: VISA | R45: =M45-N45-O45 -> 167.58 | S45: =R45/E45 -> 167.58 | T45: AGOSTO | U45: =M45/2-O45/2 -> 87.39 | V45: Plataforma Stone
T46: SETEMBRO | U46: =U45 -> 87.39
B47: 2470 | C47: CAMISA CHAMPIONS | D47: VENDA | E47: 1 | F47: SAÍDA | G47: 45853 | H47: TERÇA | I47: 3433 - CONSUMIDOR FINAL | J47: 1042 | K47: 180 | L47: 0 | M47: =K47-L47 -> 180 | N47: =M47*C2 -> 7.2 | O47: =M47*1.65% -> 2.97 | P47: DÉBITO | Q47: VISA | R47: =M47-N47-O47 -> 169.83 | S47: =R47/E47 -> 169.83 | T47: JULHO | U47: =M47-O47 -> 177.03 | V47: Plataforma Stone
B48: 2470 | C48: CAMISA CHAMPIONS | D48: VENDA | E48: 1 | F48: SAÍDA | G48: 45853 | H48: TERÇA | I48: 3433 - CONSUMIDOR FINAL | J48: 1043 | K48: 180 | L48: 0 | M48: =K48-L48 -> 180 | N48: =M48*C2 -> 7.2 | O48: =M48*0.75% -> 1.35 | P48: PIX | Q48: - | R48: =M48-N48-O48 -> 171.45 | S48: =R48/E48 -> 171.45 | T48: JULHO | U48: =M48-O48 -> 178.65 | V48: Plataforma Stone
B49: 2470 | C49: CAMISA CHAMPIONS | D49: VENDA | E49: 1 | F49: SAÍDA | G49: 45853 | H49: TERÇA | I49: 3433 - CONSUMIDOR FINAL | J49: 1044 | K49: 360 | L49: 72 | M49: =K49-L49 -> 288 | N49: =M49*C2 -> 11.52 | O49: =M49*2.05% -> 5.904 | P49: DÉBITO | Q49: ELO | R49: =M49-N49-O49 -> 270.576 | S49: =R49/E49 -> 270.576 | T49: JULHO | U49: =M49-O49 -> 282.096 | V49: Plataforma Stone
B50: 3006 | C50: REGATA BASQUETE | D50: VENDA | E50: 1 | F50: SAÍDA | G50: 45853 | H50: TERÇA | I50: 3433 - CONSUMIDOR FINAL | J50: 1045 | K50: 170 | L50: 0 | M50: =K50-L50 -> 170 | N50: =M50*C2 -> 6.8 | O50: =M50*2.9% -> 4.93 | P50: CRÉDITO 2X | Q50: VISA | R50: =M50-N50-O50 -> 158.27 | S50: =R50/E50 -> 158.27 | T50: AGOSTO | U50: =M50/2-O50/2 -> 82.535 | V50: Plataforma Stone
T51: SETEMBRO | U51: =U50 -> 82.535
B52: 2470 | C52: CAMISA CHAMPIONS | D52: VENDA | E52: 1 | F52: SAÍDA | G52: 45854 | H52: QUARTA | I52: 3433 - CONSUMIDOR FINAL | J52: 1046 | K52: 180 | L52: 36 | M52: =K52-L52 -> 144 | N52: =M52*C2 -> 5.76 | O52: =M52*1.65% -> 2.376 | P52: DÉBITO | Q52: VISA | R52: =M52-N52-O52 -> 135.864 | S52: =R52/E52 -> 135.864 | T52: JULHO | U52: =M52-O52 -> 141.624 | V52: Plataforma Stone
B53: 3010 | C53: JAQUETA TORCEDOR | D53: VENDA | E53: 1 | F53: SAÍDA | G53: 45854 | H53: QUARTA | I53: 3433 - CONSUMIDOR FINAL | J53: 1046 | K53: 250 | L53: 50 | M53: =K53-L53 -> 200 | N53: =M53*C2 -> 8 | O53: =M53*1.65% -> 3.3 | P53: DÉBITO | Q53: VISA | R53: =M53-N53-O53 -> 188.7 | S53: =R53/E53 -> 188.7 | T53: JULHO | U53: =M53-O53 -> 196.7 | V53: Plataforma Stone
B54: 2470 | C54: CAMISA CHAMPIONS | D54: VENDA | E54: 1 | F54: SAÍDA | G54: 45854 | H54: QUARTA | I54: 3433 - CONSUMIDOR FINAL | J54: 1047 | K54: 180 | L54: 0 | M54: =K54-L54 -> 180 | N54: =M54*C2 -> 7.2 | O54: 5.22 | P54: CRÉDITO 2X | Q54: VISA | R54: =M54-N54-O54 -> 167.58 | S54: =R54/E54 -> 167.58 | T54: AGOSTO | U54: =M54/2-O54/2 -> 87.39 | V54: Plataforma Stone
T55: SETEMBRO | U55: =U54 -> 87.39
B56: 3010 | C56: JAQUETA TORCEDOR | D56: VENDA | E56: 1 | F56: SAÍDA | G56: 45855 | H56: QUINTA | I56: 3433 - CONSUMIDOR FINAL | J56: 1048 | K56: 250 | L56: 50 | M56: =K56-L56 -> 200 | N56: =M56*C2 -> 8 | O56: =M56*1.65% -> 3.3 | P56: DÉBITO | Q56: VISA | R56: =M56-N56-O56 -> 188.7 | S56: =R56/E56 -> 188.7 | T56: JULHO | U56: =M56-O56 -> 196.7 | V56: Plataforma Stone
B57: 3008 | C57: CAMISA OFICIAL | D57: VENDA | E57: 3 | F57: SAÍDA | G57: 45855 | H57: QUINTA | I57: 3433 - CONSUMIDOR FINAL | J57: 1048 | K57: 645 | L57: 129 | M57: =K57-L57 -> 516 | N57: =M57*C2 -> 20.64 | O57: =16*1.65% -> 0.264 | P57: DÉBITO | Q57: VISA | R57: =M57-N57-O57-O58 -> 480.596 | S57: =(R57+R58)/E57 -> 160.19867 | T57: JULHO | U57: =16-O57 -> 15.736 | V57: Plataforma Stone
O58: =500*2.9% -> 14.5 | P58: CRÉDITO 2X | Q58: VISA | T58: AGOSTO | U58: =250-(O58/2) -> 242.75 | V58: Plataforma Stone
T59: SETEMBRO | U59: =U58 -> 242.75
B60: 2470 | C60: CAMISA CHAMPIONS | D60: VENDA | E60: 1 | F60: SAÍDA | G60: 45856 | H60: SEXTA | I60: 3433 - CONSUMIDOR FINAL | J60: 1049 | K60: 180 | L60: 0 | M60: =K60-L60 -> 180 | N60: =M60*C2 -> 7.2 | O60: =M60*2.05% -> 3.69 | P60: DÉBITO | Q60: ELO | R60: =M60-N60-O60 -> 169.11 | S60: =R60/E60 -> 169.11 | T60: JULHO | U60: =M60-O60 -> 176.31 | V60: Plataforma Stone
B61: 2470 | C61: CAMISA CHAMPIONS | D61: VENDA | E61: 1 | F61: SAÍDA | G61: 45856 | H61: SEXTA | I61: 3433 - CONSUMIDOR FINAL | J61: 1050 | K61: 180 | L61: 0 | M61: =K61-L61 -> 180 | N61: =M61*C2 -> 7.2 | O61: =M61*2.9% -> 5.22 | P61: CRÉDITO 2X | Q61: VISA | R61: =M61-N61-O61 -> 167.58 | S61: =R61/E61 -> 167.58 | T61: AGOSTO | U61: =M61/2-O61/2 -> 87.39 | V61: Plataforma Stone
T62: SETEMBRO | U62: =U61 -> 87.39
B63: 2470 | C63: CAMISA CHAMPIONS | D63: VENDA | E63: 1 | F63: SAÍDA | G63: 45856 | H63: SEXTA | I63: 3433 - CONSUMIDOR FINAL | J63: 1051 | K63: 180 | L63: 0 | M63: =K63-L63 -> 180 | N63: =M63*C2 -> 7.2 | O63: =M63*1.9% -> 3.42 | P63: DÉBITO | Q63: VISA | R63: =M63-N63-O74 -> 166.878 | S63: =R63/E63 -> 166.878 | T63: JUNHO | U63: =M63-O63 -> 176.58 | V63: Venda dia 22/06
B64: 2470 | C64: CAMISA CHAMPIONS | D64: VENDA | E64: 2 | F64: SAÍDA | G64: 45856 | H64: - | I64: 3433 - CONSUMIDOR FINAL | J64: 1052 | K64: 360 | L64: 0 | M64: =K64-L64 -> 360 | N64: =M64*C2 -> 14.4 | O64: 0 | P64: PIX | Q64: - | R64: =M64-N64-O64 -> 345.6 | S64: =R64/E64 -> 172.8 | T64: JUNHO | U64: =M64-O64 -> 360 | V64: Pix dia 23/06
B65: 2550 | C65: BONÉ LUXO | D65: VENDA | E65: 1 | F65: SAÍDA | G65: 45856 | H65: - | I65: 3433 - CONSUMIDOR FINAL | J65: 1053 | K65: 60 | L65: 0 | M65: =K65-L65 -> 60 | N65: =M65*C2 -> 2.4 | O65: 0 | P65: PIX | Q65: - | R65: =M65-N65-O65 -> 57.6 | S65: =R65/E65 -> 57.6 | T65: JUNHO | U65: =M65-O65 -> 60 | V65: Pix dia 20/06
B66: 3010 | C66: JAQUETA TORCEDOR | D66: VENDA | E66: 1 | F66: SAÍDA | G66: 45856 | H66: SEXTA | I66: 3433 - CONSUMIDOR FINAL | J66: 1054 | K66: 250 | L66: 50 | M66: =K66-L66 -> 200 | N66: =M66*C2 -> 8 | O66: =M66*3.71% -> 7.42 | P66: CRÉDITO 2X | Q66: ELO | R66: =M66-N66-O66 -> 184.58 | S66: =R66/E66 -> 184.58 | T66: AGOSTO | U66: =M66/2-O66/2 -> 96.29 | V66: Plataforma Stone
T67: SETEMBRO | U67: =U66 -> 96.29
B68: 2550 | C68: BONÉ LUXO | D68: VENDA | E68: 1 | F68: SAÍDA | G68: 45856 | H68: SEXTA | I68: 3433 - CONSUMIDOR FINAL | J68: 1054 | K68: 60 | L68: 12 | M68: =K68-L68 -> 48 | N68: =M68*C2 -> 1.92 | O68: =M68*3.71% -> 1.7808 | P68: CRÉDITO 2X | Q68: ELO | R68: =M68-N68-O68 -> 44.2992 | S68: =R68/E68 -> 44.2992 | T68: AGOSTO | U68: =M68/2-O68/2 -> 23.1096 | V68: Plataforma Stone
T69: SETEMBRO | U69: =U68 -> 23.1096
B70: 2470 | C70: CAMISA CHAMPIONS | D70: VENDA | E70: 2 | F70: SAÍDA | G70: 45857 | H70: SÁBADO | I70: 3433 - CONSUMIDOR FINAL | J70: 1055 | K70: 360 | L70: 36 | M70: =K70-L70 -> 324 | N70: =M70*C2 -> 12.96 | O70: =M70*2.9% -> 9.396 | P70: CRÉDITO 2X | Q70: MASTERCARD | R70: =M70-N70-O70 -> 301.644 | S70: =R70/E70 -> 150.822 | T70: AGOSTO | U70: =M70/2-O70/2 -> 157.302 | V70: Plataforma Stone
T71: SETEMBRO | U71: =U70 -> 157.302
B72: 2470 | C72: CAMISA CHAMPIONS | D72: VENDA | E72: 1 | F72: SAÍDA | G72: 45857 | H72: SÁBADO | I72: 3433 - CONSUMIDOR FINAL | J72: 1056 | K72: 180 | L72: 0 | M72: =K72-L72 -> 180 | N72: =M72*C2 -> 7.2 | O72: =M72*3.78% -> 6.804 | P72: CRÉDITO 2X | Q72: VISA | R72: =M72-N72-O72 -> 165.996 | S72: =R72/E72 -> 165.996 | T72: AGOSTO | U72: =M72/2-O72/2 -> 86.598
T73: SETEMBRO | U73: =U72 -> 86.598
B74: 2470 | C74: CAMISA CHAMPIONS | D74: VENDA | E74: 1 | F74: SAÍDA | G74: 45857 | H74: SÁBADO | I74: 3433 - CONSUMIDOR FINAL | J74: 1057 | K74: 180 | L74: 0 | M74: =K74-L74 -> 180 | N74: =M74*C2 -> 7.2 | O74: =M63*3.29% -> 5.922 | P74: CRÉDITO | Q74: MASTERCARD | R74: =M74-N74-O74 -> 166.878 | S74: =R74/E74 -> 166.878 | T74: AGOSTO | U74: =M63-O74 -> 174.078
B75: 2470 | C75: CAMISA CHAMPIONS | D75: VENDA | E75: 1 | F75: SAÍDA | G75: 45857 | H75: SÁBADO | I75: 3433 - CONSUMIDOR FINAL | J75: 1058 | K75: 180 | L75: 0 | M75: =K75-L75 -> 180 | N75: =M75*C2 -> 7.2 | O75: =M75*1.9% -> 3.42 | P75: DÉBITO | Q75: VISA | R75: =M75-N75-O75 -> 169.38 | S75: =R75/E75 -> 169.38 | T75: JULHO | U75: =M75-O75 -> 176.58
B76: 3010 | C76: JAQUETA TORCEDOR | D76: VENDA | E76: 1 | F76: SAÍDA | G76: 45857 | H76: - | I76: 3433 - CONSUMIDOR FINAL | J76: 1059 | K76: 250 | L76: 0 | M76: =K76-L76 -> 250 | N76: =M76*C2 -> 10 | O76: =M76*2.9% -> 7.25 | P76: CRÉDITO 2X | Q76: VISA | R76: =M76-N76-O76 -> 232.75 | S76: =R76/E76 -> 232.75 | T76: AGOSTO | U76: =M76/2-O76/2 -> 121.375 | V76: Plataforma Stone / Venda externa
T77: SETEMBRO | U77: =U76 -> 121.375
B78: 2470 | C78: CAMISA CHAMPIONS | D78: VENDA | E78: 1 | F78: SAÍDA | G78: 45857 | H78: SÁBADO | I78: 3433 - CONSUMIDOR FINAL | J78: 1060 | K78: 180 | L78: 36 | M78: =K78-L78 -> 144 | N78: =M78*C2 -> 5.76 | O78: =M78*1.65% -> 2.376 | P78: DÉBITO | Q78: MASTERCARD | R78: =M78-N78-O78 -> 135.864 | S78: =R78/E78 -> 135.864 | T78: JULHO | U78: =M78-O78 -> 141.624 | V78: Plataforma Stone
B79: 2470 | C79: CAMISA CHAMPIONS | D79: VENDA | E79: 1 | F79: SAÍDA | G79: 45857 | H79: SÁBADO | I79: 3433 - CONSUMIDOR FINAL | J79: 1061 | K79: 180 | L79: 36 | M79: =K79-L79 -> 144 | N79: =M79*C2 -> 5.76 | O79: =M79*2.7% -> 3.888 | P79: CRÉDITO | Q79: MASTERCARD | R79: =M79-N79-O79 -> 134.352 | S79: =R79/E79 -> 134.352 | T79: AGOSTO | U79: =M79-O79 -> 140.112 | V79: Plataforma Stone
B80: 2470 | C80: CAMISA CHAMPIONS | D80: VENDA | E80: 4 | F80: SAÍDA | G80: 45857 | H80: - | I80: 3433 - CONSUMIDOR FINAL | J80: 1062 | K80: 720 | L80: 144 | M80: =K80-L80 -> 576 | N80: =M80*C2 -> 23.04 | O80: =M80*2.9% -> 16.704 | P80: CRÉDITO 4X | Q80: VISA | R80: =M80-N80-O80 -> 536.256 | S80: =R80/E80 -> 134.064 | T80: AGOSTO | U80: =M80/4-O80/4 -> 139.824 | V80: Plataforma Stone / Venda externa
T81: SETEMBRO | U81: =U80 -> 139.824
T82: OUTUBRO | U82: =U81 -> 139.824
T83: NOVEMBRO | U83: =U82 -> 139.824
B84: 2470 | C84: CAMISA CHAMPIONS | D84: VENDA | E84: 1 | F84: SAÍDA | G84: 45859 | H84: SEGUNDA | I84: 3433 - CONSUMIDOR FINAL | J84: 1063 | K84: 180 | L84: 50 | M84: =K84-L84 -> 130 | N84: =M84*C2 -> 5.2 | O84: =M84*1.65%-0.01 -> 2.135 | P84: DÉBITO | Q84: VISA | R84: =M84-N84-O84 -> 122.665 | S84: =R84/E84 -> 122.665 | T84: JULHO | U84: =M84-O84 -> 127.865 | V84: Plataforma Stone
B85: 2470 | C85: CAMISA CHAMPIONS | D85: VENDA | E85: 1 | F85: SAÍDA | G85: 45860 | H85: TERÇA | I85: 3433 - CONSUMIDOR FINAL | J85: 1066 | K85: 180 | L85: 0 | M85: =K85-L85 -> 180 | N85: =M85*C2 -> 7.2 | O85: =M85*2.9% -> 5.22 | P85: CRÉDITO 2X | Q85: VISA | R85: =M85-N85-O85 -> 167.58 | S85: =R85/E85 -> 167.58 | T85: AGOSTO | U85: =M85/2-O85/2 -> 87.39 | V85: Plataforma Stone
T86: SETEMBRO | U86: =U85 -> 87.39
B87: 2470 | C87: CAMISA CHAMPIONS | D87: VENDA | E87: 1 | F87: SAÍDA | G87: 45861 | H87: QUARTA | I87: 3433 - CONSUMIDOR FINAL | J87: 1067 | K87: 180 | L87: 0 | M87: =K87-L87 -> 180 | N87: =M87*C2 -> 7.2 | O87: =M87*0.75% -> 1.35 | P87: PIX | Q87: - | R87: =M87-N87-O87 -> 171.45 | S87: =R87/E87 -> 171.45 | T87: JULHO | U87: =M87-O87 -> 178.65 | V87: Plataforma Stone
B88: 2470 | C88: CAMISA CHAMPIONS | D88: VENDA | E88: 2 | F88: SAÍDA | G88: 45861 | H88: QUARTA | I88: 6361 - ANA CAROLINA | J88: 1068 | K88: 360 | L88: 80 | M88: =K88-L88 -> 280 | N88: =M88*C2 -> 11.2 | O88: =M88*2.91%-0.03 -> 8.118 | P88: CRÉDITO 2X | Q88: VISA | R88: =M88-N88-O88 -> 260.682 | S88: =R88/E88 -> 130.341 | T88: AGOSTO | U88: =M88/2-O88/2 -> 135.941 | V88: Plataforma Stone
T89: SETEMBRO | U89: =U88 -> 135.941
B90: 2470 | C90: CAMISA CHAMPIONS | D90: VENDA | E90: 1 | F90: SAÍDA | G90: 45861 | H90: - | I90: 3433 - CONSUMIDOR FINAL | J90: 1069 | K90: 180 | L90: 0 | M90: =K90-L90 -> 180 | N90: =M90*C2 -> 7.2 | O90: 0 | P90: PIX | Q90: - | R90: =M90-N90-O90 -> 172.8 | S90: =R90/E90 -> 172.8 | T90: JUNHO | V90: Venda feita dia 27/06
B91: 3010 | C91: JAQUETA TORCEDOR | D91: VENDA | E91: 1 | F91: SAÍDA | G91: 45861 | H91: - | I91: 3433 - CONSUMIDOR FINAL | J91: 1069 | K91: 250 | L91: 0 | M91: =K91-L91 -> 250 | N91: =M91*C2 -> 10 | O91: 0 | P91: PIX | Q91: - | R91: =M91-N91-O91 -> 240 | S91: =R91/E91 -> 240 | T91: JUNHO | V91: Venda feita dia 27/06
B92: 2470 | C92: CAMISA CHAMPIONS | D92: VENDA | E92: 1 | F92: SAÍDA | G92: 45861 | H92: QUARTA | I92: 3433 - CONSUMIDOR FINAL | J92: 1070 | K92: 180 | L92: 0 | M92: =K92-L92 -> 180 | N92: =M92*C2 -> 7.2 | O92: =M92*2.9% -> 5.22 | P92: CRÉDITO 2X | Q92: MASTERCARD | R92: =M92-N92-O92 -> 167.58 | S92: =R92/E92 -> 167.58 | T92: AGOSTO | U92: =M92/2-O92/2 -> 87.39 | V92: Plataforma Stone
T93: SETEMBRO | U93: =U92 -> 87.39
B94: 2470 | C94: CAMISA CHAMPIONS | D94: VENDA | E94: 1 | F94: SAÍDA | G94: 45861 | H94: - | I94: 3433 - CONSUMIDOR FINAL | J94: 1071 | K94: 180 | L94: 0 | M94: =K94-L94 -> 180 | N94: =M94*C2 -> 7.2 | O94: 0 | P94: PIX | Q94: - | R94: =M94-N94-O94 -> 172.8 | S94: =R94/E94 -> 172.8 | T94: JUNHO | V94: Venda feita dia 30/06
B95: 2470 | C95: CAMISA CHAMPIONS | D95: VENDA | E95: 1 | F95: SAÍDA | G95: 45861 | H95: - | I95: 3433 - CONSUMIDOR FINAL | J95: 1072 | K95: 180 | L95: 0 | M95: =K95-L95 -> 180 | N95: =M95*C2 -> 7.2 | O95: =M95*3.78% -> 6.804 | P95: CRÉDITO 3X | Q95: MASTERCARD | R95: =M95-N95-O95 -> 165.996 | S95: =R95/E95 -> 165.996 | T95: JULHO | U95: =M95/3-O95/3 -> 57.732 | V95: Venda feita dia 02/06
T96: AGOSTO | U96: =U95 -> 57.732
T97: SETEMBRO | U97: =U96 -> 57.732
B98: 2550 | C98: BONÉ LUXO | D98: VENDA | E98: 1 | F98: SAÍDA | G98: 45861 | H98: - | I98: 3433 - CONSUMIDOR FINAL | J98: 1072 | K98: 60 | L98: 0 | M98: =K98-L98 -> 60 | N98: =M98*C2 -> 2.4 | O98: =M98*3.78% -> 2.268 | P98: CRÉDITO 3X | Q98: MASTERCARD | R98: =M98-N98-O98 -> 55.332 | S98: =R98/E98 -> 55.332 | T98: JULHO | U98: =M98/3-O98/3 -> 19.244
T99: AGOSTO | U99: =U98 -> 19.244
T100: SETEMBRO | U100: =U99 -> 19.244
...

Sheet SALDO QTD
B2: 2470 | C2: CAMISA CHAMPIONS | I2: 2550 | J2: BONÉ LUXO
B3: ESTOQUE NO 2° TRIM. | E3: 823 | I3: ESTOQUE NO 2° TRIM. | L3: 107
B4: MÊS/PERÍODO | C4: COMPRA | D4: VENDA | E4: DOAÇÃO | F4: DEVOLUÇÃO | G4: ESTOQUE FINAL | I4: MÊS/PERÍODO | J4: COMPRA | K4: VENDA | L4: DOAÇÃO | M4: DEVOLUÇÃO | N4: ESTOQUE FINAL
B5: 45839 | C5: =SUMIFS(MOVIMENTO!E4:E153,MOVIMENTO!B4:B153,B2,MOVIMENTO!D4:D153,C4) -> 0 | D5: =SUMIFS(MOVIMENTO!E4:E153,MOVIMENTO!B4:B153,B2,MOVIMENTO!D4:D153,D4) -> 178 | E5: =SUMIFS(MOVIMENTO!E4:E153,MOVIMENTO!B4:B153,B2,MOVIMENTO!D4:D153,E4) -> 0 | F5: =SUMIFS(MOVIMENTO!E4:E153,MOVIMENTO!B4:B153,B2,MOVIMENTO!D4:D153,F4) -> 0 | G5: =(E3+C5+F5)-(D5+E5) -> 645 | I5: 45839 | J5: =SUMIFS(MOVIMENTO!E4:E153,MOVIMENTO!B4:B153,I2,MOVIMENTO!D4:D153,J4) -> 0 | K5: =SUMIFS(MOVIMENTO!E4:E153,MOVIMENTO!B4:B153,I2,MOVIMENTO!D4:D153,K4) -> 14 | L5: =SUMIFS(MOVIMENTO!E4:E153,MOVIMENTO!B4:B153,I2,MOVIMENTO!D4:D153,L4) -> 0 | M5: =SUMIFS(MOVIMENTO!E4:E153,MOVIMENTO!B4:B153,I2,MOVIMENTO!D4:D153,M4) -> 0 | N5: =SUM(L3+J5+M5)-(K5+L5) -> 93
B6: 45870 | C6: =SUMIFS(MOVIMENTO!E155:E363,MOVIMENTO!B155:B363,B2,MOVIMENTO!D155:D363,C4) -> 0 | D6: =SUMIFS(MOVIMENTO!E155:E363,MOVIMENTO!B155:B363,B2,MOVIMENTO!D155:D363,D4) -> 198 | E6: =SUMIFS(MOVIMENTO!E155:E363,MOVIMENTO!B155:B363,B2,MOVIMENTO!D155:D363,E4) -> 0 | F6: =SUMIFS(MOVIMENTO!E155:E363,MOVIMENTO!B155:B363,B2,MOVIMENTO!D155:D363,F4) -> 11 | G6: =(G5+F6+C6)-(D6+E6) -> 458 | I6: 45870 | J6: =SUMIFS(MOVIMENTO!E155:E363,MOVIMENTO!B155:B363,I2,MOVIMENTO!D155:D363,J4) -> 0 | K6: =SUMIFS(MOVIMENTO!E155:E363,MOVIMENTO!B155:B363,I2,MOVIMENTO!D155:D363,K4) -> 12 | L6: =SUMIFS(MOVIMENTO!E155:E363,MOVIMENTO!B155:B363,I2,MOVIMENTO!D155:D363,L4) -> 0 | M6: =SUMIFS(MOVIMENTO!E155:E363,MOVIMENTO!B155:B363,I2,MOVIMENTO!D155:D363,M4) -> 2 | N6: =(N5+J6+M6)-(K6+L6) -> 83
B7: 45901 | C7: =SUMIFS(MOVIMENTO!E364:E421,MOVIMENTO!B364:B421,B2,MOVIMENTO!D364:D421,C4) -> 0 | D7: =SUMIFS(MOVIMENTO!E364:E421,MOVIMENTO!B364:B421,B2,MOVIMENTO!D364:D421,D4) -> 36 | E7: =SUMIFS(MOVIMENTO!E364:E421,MOVIMENTO!B364:B421,B2,MOVIMENTO!D364:D421,E4) -> 0 | F7: =SUMIFS(MOVIMENTO!E364:E421,MOVIMENTO!B364:B421,B2,MOVIMENTO!D364:D421,F4) -> 0 | G7: =(G6+F7+C7)-(D7+E7) -> 422 | I7: 45901 | J7: =SUMIFS(MOVIMENTO!E364:E421,MOVIMENTO!B364:B421,I2,MOVIMENTO!D364:D421,J4) -> 0 | K7: =SUMIFS(MOVIMENTO!E364:E421,MOVIMENTO!B364:B421,I2,MOVIMENTO!D364:D421,K4) -> 3 | L7: =SUMIFS(MOVIMENTO!E364:E421,MOVIMENTO!B364:B421,I2,MOVIMENTO!D364:D421,L4) -> 0 | M7: =SUMIFS(MOVIMENTO!E364:E421,MOVIMENTO!B364:B421,I2,MOVIMENTO!D364:D421,M4) -> 0 | N7: =(N6+M7+J7)-(K7+L7) -> 80
B9: 2731 | C9: BONÉ BRIM | I9: 2946 | J9: MASCOTE PORTO
B10: ESTOQUE NO 2° TRIM. | E10: 12 | I10: ESTOQUE NO 2° TRIM. | L10: 273
B11: MÊS/PERÍODO | C11: COMPRA | D11: VENDA | E11: DOAÇÃO | F11: DEVOLUÇÃO | G11: ESTOQUE FINAL | I11: MÊS/PERÍODO | J11: COMPRA | K11: VENDA | L11: DOAÇÃO | M11: DEVOLUÇÃO | N11: ESTOQUE FINAL
B12: 45839 | C12: =SUMIFS(MOVIMENTO!E4:E153,MOVIMENTO!B4:B153,B9,MOVIMENTO!D4:D153,C11) -> 0 | D12: =SUMIFS(MOVIMENTO!E4:E153,MOVIMENTO!B4:B153,B9,MOVIMENTO!D4:D153,D11) -> 1 | E12: =SUMIFS(MOVIMENTO!E4:E153,MOVIMENTO!B4:B153,B9,MOVIMENTO!D4:D153,E11) -> 0 | F12: =SUMIFS(MOVIMENTO!E4:E153,MOVIMENTO!B4:B153,B9,MOVIMENTO!D4:D153,F11) -> 0 | G12: =(E10+C12+F12)-(D12+E12) -> 11 | I12: 45839 | J12: =SUMIFS(MOVIMENTO!E4:E153,MOVIMENTO!B4:B153,I9,MOVIMENTO!D4:D153,J11) -> 0 | K12: =SUMIFS(MOVIMENTO!E4:E153,MOVIMENTO!B4:B153,I9,MOVIMENTO!D4:D153,K11) -> 1 | L12: =SUMIFS(MOVIMENTO!E4:E153,MOVIMENTO!B4:B153,I9,MOVIMENTO!D4:D153,L11) -> 0 | M12: =SUMIFS(MOVIMENTO!E4:E153,MOVIMENTO!B4:B153,I9,MOVIMENTO!D4:D153,M11) -> 0 | N12: =SUM(L10+J12+M12)-(K12+L12) -> 272
B13: 45870 | C13: =SUMIFS(MOVIMENTO!E155:E363,MOVIMENTO!B155:B363,B9,MOVIMENTO!D155:D363,C11) -> 0 | D13: =SUMIFS(MOVIMENTO!E155:E363,MOVIMENTO!B155:B363,B9,MOVIMENTO!D155:D363,D11) -> 0 | E13: =SUMIFS(MOVIMENTO!E155:E363,MOVIMENTO!B155:B363,B9,MOVIMENTO!D155:D363,E11) -> 0 | F13: =SUMIFS(MOVIMENTO!E155:E363,MOVIMENTO!B155:B363,B9,MOVIMENTO!D155:D363,F11) -> 0 | G13: =(G12+C13)-(D13+E13-F13) -> 11 | I13: 45870 | J13: =SUMIFS(MOVIMENTO!E155:E363,MOVIMENTO!B155:B363,I9,MOVIMENTO!D155:D363,J11) -> 0 | K13: =SUMIFS(MOVIMENTO!E155:E363,MOVIMENTO!B155:B363,I9,MOVIMENTO!D155:D363,K11) -> 7 | L13: =SUMIFS(MOVIMENTO!E155:E363,MOVIMENTO!B155:B363,I9,MOVIMENTO!D155:D363,L11) -> 0 | M13: =SUMIFS(MOVIMENTO!E155:E363,MOVIMENTO!B155:B363,I9,MOVIMENTO!D155:D363,M11) -> 0 | N13: =(N12+J13)-(K13+L13-M13) -> 265
B14: 45901 | C14: =SUMIFS(MOVIMENTO!E364:E421,MOVIMENTO!B364:B421,B9,MOVIMENTO!D364:D421,C11) -> 0 | D14: =SUMIFS(MOVIMENTO!E364:E421,MOVIMENTO!B364:B421,B9,MOVIMENTO!D364:D421,D11) -> 0 | E14: =SUMIFS(MOVIMENTO!E364:E421,MOVIMENTO!B364:B421,B9,MOVIMENTO!D364:D421,E11) -> 0 | F14: =SUMIFS(MOVIMENTO!E364:E421,MOVIMENTO!B364:B421,B9,MOVIMENTO!D364:D421,F11) -> 0 | G14: =(G13+C14)-(D14+E14-F14) -> 11 | I14: 45901 | J14: =SUMIFS(MOVIMENTO!E364:E421,MOVIMENTO!B364:B421,I9,MOVIMENTO!D364:D421,J11) -> 0 | K14: =SUMIFS(MOVIMENTO!E364:E421,MOVIMENTO!B364:B421,I9,MOVIMENTO!D364:D421,K11) -> 0 | L14: =SUMIFS(MOVIMENTO!E364:E421,MOVIMENTO!B364:B421,I9,MOVIMENTO!D364:D421,L11) -> 0 | M14: =SUMIFS(MOVIMENTO!E364:E421,MOVIMENTO!B364:B421,I9,MOVIMENTO!D364:D421,M11) -> 0 | N14: =(N13+J14)-(K14+L14-M14) -> 265
B16: 2953 | C16: COPO TÉRMICO TULIP 500ML | I16: 2957 | J16: GARRAFA 660ML
B17: ESTOQUE NO 2° TRIM. | E17: 140 | I17: ESTOQUE NO 2° TRIM. | L17: 1
B18: MÊS/PERÍODO | C18: COMPRA | D18: VENDA | E18: DOAÇÃO | F18: DEVOLUÇÃO | G18: ESTOQUE FINAL | I18: MÊS/PERÍODO | J18: COMPRA | K18: VENDA | L18: DOAÇÃO | M18: DEVOLUÇÃO | N18: ESTOQUE FINAL
B19: 45839 | C19: =SUMIFS(MOVIMENTO!E4:E153,MOVIMENTO!B4:B153,B16,MOVIMENTO!D4:D153,C18) -> 0 | D19: =SUMIFS(MOVIMENTO!E4:E153,MOVIMENTO!B4:B153,B16,MOVIMENTO!D4:D153,D18) -> 0 | E19: =SUMIFS(MOVIMENTO!E4:E153,MOVIMENTO!B4:B153,B16,MOVIMENTO!D4:D153,E18) -> 0 | F19: =SUMIFS(MOVIMENTO!E4:E153,MOVIMENTO!B4:B153,B16,MOVIMENTO!D4:D153,F18) -> 0 | G19: =SUM(E17+C19+F19)-(D19+E19) -> 140 | I19: 45839 | J19: =SUMIFS(MOVIMENTO!E4:E153,MOVIMENTO!B4:B153,I16,MOVIMENTO!D4:D153,J18) -> 0 | K19: =SUMIFS(MOVIMENTO!E4:E153,MOVIMENTO!B4:B153,I16,MOVIMENTO!D4:D153,K18) -> 0 | L19: =SUMIFS(MOVIMENTO!E4:E153,MOVIMENTO!B4:B153,I16,MOVIMENTO!D4:D153,L18) -> 0 | M19: =SUMIFS(MOVIMENTO!E4:E153,MOVIMENTO!B4:B153,I16,MOVIMENTO!D4:D153,M18) -> 0 | N19: =(J19+M19+L17)-(K19+L19) -> 1
B20: 45870 | C20: =SUMIFS(MOVIMENTO!E155:E363,MOVIMENTO!B155:B363,B16,MOVIMENTO!D155:D363,C18) -> 0 | D20: =SUMIFS(MOVIMENTO!E155:E363,MOVIMENTO!B155:B363,B16,MOVIMENTO!D155:D363,D18) -> 3 | E20: =SUMIFS(MOVIMENTO!E155:E363,MOVIMENTO!B155:B363,B16,MOVIMENTO!D155:D363,E18) -> 0 | F20: =SUMIFS(MOVIMENTO!E155:E363,MOVIMENTO!B155:B363,B16,MOVIMENTO!D155:D363,F18) -> 0 | G20: =(G19+C20)-(D20+E20-F20) -> 137 | I20: 45870 | J20: =SUMIFS(MOVIMENTO!E155:E363,MOVIMENTO!B155:B363,I16,MOVIMENTO!D155:D363,J18) -> 0 | K20: =SUMIFS(MOVIMENTO!E155:E363,MOVIMENTO!B155:B363,I16,MOVIMENTO!D155:D363,K18) -> 0 | L20: =SUMIFS(MOVIMENTO!E155:E363,MOVIMENTO!B155:B363,I16,MOVIMENTO!D155:D363,L18) -> 0 | M20: =SUMIFS(MOVIMENTO!E155:E363,MOVIMENTO!B155:B363,I16,MOVIMENTO!D155:D363,M18) -> 0 | N20: =(J20+M20+N19)-(K20+L20) -> 1
B21: 45901 | C21: =SUMIFS(MOVIMENTO!E364:E421,MOVIMENTO!B364:B421,B16,MOVIMENTO!D364:D421,C18) -> 0 | D21: =SUMIFS(MOVIMENTO!E364:E421,MOVIMENTO!B364:B421,B16,MOVIMENTO!D364:D421,D18) -> 0 | E21: =SUMIFS(MOVIMENTO!E364:E421,MOVIMENTO!B364:B421,B16,MOVIMENTO!D364:D421,E18) -> 0 | F21: =SUMIFS(MOVIMENTO!E364:E421,MOVIMENTO!B364:B421,B16,MOVIMENTO!D364:D421,F18) -> 0 | G21: =(G20+C21)-(D21+E21-F21) -> 137 | I21: 45901 | J21: =SUMIFS(MOVIMENTO!E364:E421,MOVIMENTO!B364:B421,I16,MOVIMENTO!D364:D421,J18) -> 0 | K21: =SUMIFS(MOVIMENTO!E364:E421,MOVIMENTO!B364:B421,I16,MOVIMENTO!D364:D421,K18) -> 0 | L21: =SUMIFS(MOVIMENTO!E364:E421,MOVIMENTO!B364:B421,I16,MOVIMENTO!D364:D421,L18) -> 0 | M21: =SUMIFS(MOVIMENTO!E364:E421,MOVIMENTO!B364:B421,I16,MOVIMENTO!D364:D421,M18) -> 0 | N21: =(N20+M21+J21)-(K21+L21) -> 1
B23: 2959 | C23: CANECA PORTO | I23: 3006 | J23: REGATA BASQUETE
B24: ESTOQUE NO 2° TRIM. | E24: 48 | I24: ESTOQUE NO 2° TRIM. | L24: 60
B25: MÊS/PERÍODO | C25: COMPRA | D25: VENDA | E25: DOAÇÃO | F25: DEVOLUÇÃO | G25: ESTOQUE FINAL | I25: MÊS/PERÍODO | J25: COMPRA | K25: VENDA | L25: DOAÇÃO | M25: DEVOLUÇÃO | N25: ESTOQUE FINAL
B26: 45839 | C26: =SUMIFS(MOVIMENTO!E4:E153,MOVIMENTO!B4:B153,B23,MOVIMENTO!D4:D153,C25) -> 0 | D26: =SUMIFS(MOVIMENTO!E4:E153,MOVIMENTO!B4:B153,B23,MOVIMENTO!D4:D153,D25) -> 0 | E26: =SUMIFS(MOVIMENTO!E4:E153,MOVIMENTO!B4:B153,B23,MOVIMENTO!D4:D153,E25) -> 0 | F26: =SUMIFS(MOVIMENTO!E4:E153,MOVIMENTO!B4:B153,B23,MOVIMENTO!D4:D153,F25) -> 0 | G26: =SUM(C26+E24+F26)-(D26+E26) -> 48 | I26: 45839 | J26: =SUMIFS(MOVIMENTO!E4:E153,MOVIMENTO!B4:B153,I23,MOVIMENTO!D4:D153,J25) -> 0 | K26: =SUMIFS(MOVIMENTO!E4:E153,MOVIMENTO!B4:B153,I23,MOVIMENTO!D4:D153,K25) -> 2 | L26: =SUMIFS(MOVIMENTO!E4:E153,MOVIMENTO!B4:B153,I23,MOVIMENTO!D4:D153,L25) -> 0 | M26: =SUMIFS(MOVIMENTO!E4:E153,MOVIMENTO!B4:B153,I23,MOVIMENTO!D4:D153,M25) -> 0 | N26: =(L24+M26+J26)-(K26+L26) -> 58
B27: 45870 | C27: =SUMIFS(MOVIMENTO!E155:E363,MOVIMENTO!B155:B363,B23,MOVIMENTO!D155:D363,C25) -> 0 | D27: =SUMIFS(MOVIMENTO!E155:E363,MOVIMENTO!B155:B363,B23,MOVIMENTO!D155:D363,D25) -> 0 | E27: =SUMIFS(MOVIMENTO!E155:E363,MOVIMENTO!B155:B363,B23,MOVIMENTO!D155:D363,E25) -> 0 | F27: =SUMIFS(MOVIMENTO!E155:E363,MOVIMENTO!B155:B363,B23,MOVIMENTO!D155:D363,F25) -> 0 | G27: =(G26+C27)-(D27+E27-F27) -> 48 | I27: 45870 | J27: =SUMIFS(MOVIMENTO!E155:E363,MOVIMENTO!B155:B363,I23,MOVIMENTO!D155:D363,J25) -> 0 | K27: =SUMIFS(MOVIMENTO!E155:E363,MOVIMENTO!B155:B363,I23,MOVIMENTO!D155:D363,K25) -> 7 | L27: =SUMIFS(MOVIMENTO!E155:E363,MOVIMENTO!B155:B363,I23,MOVIMENTO!D155:D363,L25) -> 0 | M27: =SUMIFS(MOVIMENTO!E155:E363,MOVIMENTO!B155:B363,I23,MOVIMENTO!D155:D363,M25) -> 0 | N27: =(N26+J27)-(K27+L27-M27) -> 51
B28: 45901 | C28: =SUMIFS(MOVIMENTO!E364:E421,MOVIMENTO!B364:B421,B23,MOVIMENTO!D364:D421,C25) -> 0 | D28: =SUMIFS(MOVIMENTO!E364:E421,MOVIMENTO!B364:B421,B23,MOVIMENTO!D364:D421,D25) -> 0 | E28: =SUMIFS(MOVIMENTO!E364:E421,MOVIMENTO!B364:B421,B23,MOVIMENTO!D364:D421,E25) -> 0 | F28: =SUMIFS(MOVIMENTO!E364:E421,MOVIMENTO!B364:B421,B23,MOVIMENTO!D364:D421,F25) -> 0 | G28: =(G27+C28)-(D28+E28-F28) -> 48 | I28: 45901 | J28: =SUMIFS(MOVIMENTO!E364:E421,MOVIMENTO!B364:B421,I23,MOVIMENTO!D364:D421,J25) -> 0 | K28: =SUMIFS(MOVIMENTO!E364:E421,MOVIMENTO!B364:B421,I23,MOVIMENTO!D364:D421,K25) -> 0 | L28: =SUMIFS(MOVIMENTO!E364:E421,MOVIMENTO!B364:B421,I23,MOVIMENTO!D364:D421,L25) -> 0 | M28: =SUMIFS(MOVIMENTO!E364:E421,MOVIMENTO!B364:B421,I23,MOVIMENTO!D364:D421,M25) -> 0 | N28: =(N27+J28)-(K28+L28-M28) -> 51
B30: 3007 | C30: CAMISA POLO | I30: 3008 | J30: CAMISA OFICIAL
B31: ESTOQUE NO 2° TRIM. | E31: 40 | I31: ESTOQUE NO 2° TRIM. | L31: 20
B32: MÊS/PERÍODO | C32: COMPRA | D32: VENDA | E32: DOAÇÃO | F32: DEVOLUÇÃO | G32: ESTOQUE FINAL | I32: MÊS/PERÍODO | J32: COMPRA | K32: VENDA | L32: DOAÇÃO | M32: DEVOLUÇÃO | N32: ESTOQUE FINAL
B33: 45839 | C33: =SUMIFS(MOVIMENTO!E4:E153,MOVIMENTO!B4:B153,B30,MOVIMENTO!D4:D153,C32) -> 0 | D33: =SUMIFS(MOVIMENTO!E4:E153,MOVIMENTO!B4:B153,B30,MOVIMENTO!D4:D153,D32) -> 2 | E33: =SUMIFS(MOVIMENTO!E4:E153,MOVIMENTO!B4:B153,B30,MOVIMENTO!D4:D153,E32) -> 0 | F33: =SUMIFS(MOVIMENTO!E4:E153,MOVIMENTO!B4:B153,B30,MOVIMENTO!D4:D153,F32) -> 0 | G33: =(E31+F33+C33)-(D33+E33) -> 38 | I33: 45839 | J33: =SUMIFS(MOVIMENTO!E4:E153,MOVIMENTO!B4:B153,I30,MOVIMENTO!D4:D153,J32) -> 0 | K33: =SUMIFS(MOVIMENTO!E4:E153,MOVIMENTO!B4:B153,I30,MOVIMENTO!D4:D153,K32) -> 8 | L33: =SUMIFS(MOVIMENTO!E4:E153,MOVIMENTO!B4:B153,I30,MOVIMENTO!D4:D153,L32) -> 0 | M33: =SUMIFS(MOVIMENTO!E4:E153,MOVIMENTO!B4:B153,I30,MOVIMENTO!D4:D153,M32) -> 0 | N33: =(L31+J33+M33)-(K33+L33) -> 12
B34: 45870 | C34: =SUMIFS(MOVIMENTO!E155:E363,MOVIMENTO!B155:B363,B30,MOVIMENTO!D155:D363,C32) -> 0 | D34: =SUMIFS(MOVIMENTO!E155:E363,MOVIMENTO!B155:B363,B30,MOVIMENTO!D155:D363,D32) -> 0 | E34: =SUMIFS(MOVIMENTO!E155:E363,MOVIMENTO!B155:B363,B30,MOVIMENTO!D155:D363,E32) -> 0 | F34: =SUMIFS(MOVIMENTO!E155:E363,MOVIMENTO!B155:B363,B30,MOVIMENTO!D155:D363,F32) -> 0 | G34: =(G33+C34)-(D34+E34-F34) -> 38 | I34: 45870 | J34: =SUMIFS(MOVIMENTO!E155:E363,MOVIMENTO!B155:B363,I30,MOVIMENTO!D155:D363,J32) -> 0 | K34: =SUMIFS(MOVIMENTO!E155:E363,MOVIMENTO!B155:B363,I30,MOVIMENTO!D155:D363,K32) -> 6 | L34: =SUMIFS(MOVIMENTO!E155:E363,MOVIMENTO!B155:B363,I30,MOVIMENTO!D155:D363,L32) -> 0 | M34: =SUMIFS(MOVIMENTO!E155:E363,MOVIMENTO!B155:B363,I30,MOVIMENTO!D155:D363,M32) -> 0 | N34: =(N33+J34)-(K34+L34-M34) -> 6
B35: 45901 | C35: =SUMIFS(MOVIMENTO!E364:E421,MOVIMENTO!B364:B421,B30,MOVIMENTO!D364:D421,C32) -> 0 | D35: =SUMIFS(MOVIMENTO!E364:E421,MOVIMENTO!B364:B421,B30,MOVIMENTO!D364:D421,D32) -> 1 | E35: =SUMIFS(MOVIMENTO!E364:E421,MOVIMENTO!B364:B421,B30,MOVIMENTO!D364:D421,E32) -> 0 | F35: =SUMIFS(MOVIMENTO!E364:E421,MOVIMENTO!B364:B421,B30,MOVIMENTO!D364:D421,F32) -> 0 | G35: =(G34+C35)-(D35+E35-F35) -> 37 | I35: 45901 | J35: =SUMIFS(MOVIMENTO!E364:E421,MOVIMENTO!B364:B421,I30,MOVIMENTO!D364:D421,J32) -> 0 | K35: =SUMIFS(MOVIMENTO!E364:E421,MOVIMENTO!B364:B421,I30,MOVIMENTO!D364:D421,K32) -> 0 | L35: =SUMIFS(MOVIMENTO!E364:E421,MOVIMENTO!B364:B421,I30,MOVIMENTO!D364:D421,L32) -> 0 | M35: =SUMIFS(MOVIMENTO!E364:E421,MOVIMENTO!B364:B421,I30,MOVIMENTO!D364:D421,M32) -> 0 | N35: =(N34+J35)-(K35+L35-M35) -> 6
B37: 3009 | C37: BERMUDA | I37: 3010 | J37: JAQUETA
B38: ESTOQUE NO 2° TRIM. | E38: 30 | I38: ESTOQUE NO 2° TRIM. | L38: 15
B39: MÊS/PERÍODO | C39: COMPRA | D39: VENDA | E39: DOAÇÃO | F39: DEVOLUÇÃO | G39: ESTOQUE FINAL | I39: MÊS/PERÍODO | J39: COMPRA | K39: VENDA | L39: DOAÇÃO | M39: DEVOLUÇÃO | N39: ESTOQUE FINAL
B40: 45839 | C40: =SUMIFS(MOVIMENTO!E4:E153,MOVIMENTO!B4:B153,B37,MOVIMENTO!D4:D153,C39) -> 0 | D40: =SUMIFS(MOVIMENTO!E4:E153,MOVIMENTO!B4:B153,B37,MOVIMENTO!D4:D153,D39) -> 0 | E40: =SUMIFS(MOVIMENTO!E4:E153,MOVIMENTO!B4:B153,B37,MOVIMENTO!D4:D153,E39) -> 0 | F40: =SUMIFS(MOVIMENTO!E4:E153,MOVIMENTO!B4:B153,B37,MOVIMENTO!D4:D153,F39) -> 0 | G40: =(E38+C40+F40)-(D40+E40) -> 30 | I40: 45839 | J40: =SUMIFS(MOVIMENTO!E4:E153,MOVIMENTO!B4:B153,I37,MOVIMENTO!D4:D153,J39) -> 0 | K40: =SUMIFS(MOVIMENTO!E4:E153,MOVIMENTO!B4:B153,I37,MOVIMENTO!D4:D153,K39) -> 8 | L40: =SUMIFS(MOVIMENTO!E4:E153,MOVIMENTO!B4:B153,I37,MOVIMENTO!D4:D153,L39) -> 0 | M40: =SUMIFS(MOVIMENTO!E4:E153,MOVIMENTO!B4:B153,I37,MOVIMENTO!D4:D153,M39) -> 0 | N40: =(M40+L38+J40)-(K40+L40) -> 7
B41: 45870 | C41: =SUMIFS(MOVIMENTO!E155:E363,MOVIMENTO!B155:B363,B37,MOVIMENTO!D155:D363,C39) -> 0 | D41: =SUMIFS(MOVIMENTO!E155:E363,MOVIMENTO!B155:B363,B37,MOVIMENTO!D155:D363,D39) -> 0 | E41: =SUMIFS(MOVIMENTO!E155:E363,MOVIMENTO!B155:B363,B37,MOVIMENTO!D155:D363,E39) -> 0 | F41: =SUMIFS(MOVIMENTO!E155:E363,MOVIMENTO!B155:B363,B37,MOVIMENTO!D155:D363,F39) -> 0 | G41: =(G40+C41)-(D41+E41-F41) -> 30 | I41: 45870 | J41: =SUMIFS(MOVIMENTO!E155:E363,MOVIMENTO!B155:B363,I37,MOVIMENTO!D155:D363,J39) -> 0 | K41: =SUMIFS(MOVIMENTO!E155:E363,MOVIMENTO!B155:B363,I37,MOVIMENTO!D155:D363,K39) -> 1 | L41: =SUMIFS(MOVIMENTO!E155:E363,MOVIMENTO!B155:B363,I37,MOVIMENTO!D155:D363,L39) -> 0 | M41: =SUMIFS(MOVIMENTO!E155:E363,MOVIMENTO!B155:B363,I37,MOVIMENTO!D155:D363,M39) -> 0 | N41: =(N40+J41+M41)-(K41+L41) -> 6
B42: 45901 | C42: =SUMIFS(MOVIMENTO!E364:E421,MOVIMENTO!B364:B421,B37,MOVIMENTO!D364:D421,C39) -> 0 | D42: =SUMIFS(MOVIMENTO!E364:E421,MOVIMENTO!B364:B421,B37,MOVIMENTO!D364:D421,D39) -> 0 | E42: =SUMIFS(MOVIMENTO!E364:E421,MOVIMENTO!B364:B421,B37,MOVIMENTO!D364:D421,E39) -> 0 | F42: =SUMIFS(MOVIMENTO!E364:E421,MOVIMENTO!B364:B421,B37,MOVIMENTO!D364:D421,F39) -> 0 | G42: =(G41+C42)-(D42+E42-F42) -> 30 | I42: 45901 | J42: =SUMIFS(MOVIMENTO!E364:E421,MOVIMENTO!B364:B421,I37,MOVIMENTO!D364:D421,J39) -> 0 | K42: =SUMIFS(MOVIMENTO!E364:E421,MOVIMENTO!B364:B421,I37,MOVIMENTO!D364:D421,K39) -> 0 | L42: =SUMIFS(MOVIMENTO!E364:E421,MOVIMENTO!B364:B421,I37,MOVIMENTO!D364:D421,L39) -> 0 | M42: =SUMIFS(MOVIMENTO!E364:E421,MOVIMENTO!B364:B421,I37,MOVIMENTO!D364:D421,M39) -> 0 | N42: =(N41+J42)-(K42+L42-M42) -> 6
B44: 3049 | C44: CAMISA RETRÔ
B45: MÊS/PERÍODO | C45: COMPRA | D45: VENDA | E45: DOAÇÃO | F45: DEVOLUÇÃO | G45: ESTOQUE FINAL
B46: 45839 | C46: =SUMIFS(MOVIMENTO!E4:E153,MOVIMENTO!B4:B153,B44,MOVIMENTO!D4:D153,C45) -> 400 | D46: =SUMIFS(MOVIMENTO!E4:E153,MOVIMENTO!B4:B153,B44,MOVIMENTO!D4:D153,D45) -> 22 | E46: =SUMIFS(MOVIMENTO!E4:E153,MOVIMENTO!B4:B153,B44,MOVIMENTO!D4:D153,E45) -> 0 | F46: =SUMIFS(MOVIMENTO!E4:E153,MOVIMENTO!B4:B153,B44,MOVIMENTO!D4:D153,F45) -> 0 | G46: =SUM(C46+F46)-(D46+E46) -> 378
B47: 45870 | C47: =SUMIFS(MOVIMENTO!E155:E363,MOVIMENTO!B155:B363,#REF!,MOVIMENTO!D155:D363,C45) -> 0 | D47: =SUMIFS(MOVIMENTO!E155:E363,MOVIMENTO!B155:B363,#REF!,MOVIMENTO!D155:D363,D45) -> 0 | E47: =SUMIFS(MOVIMENTO!E155:E363,MOVIMENTO!B155:B363,#REF!,MOVIMENTO!D155:D363,E45) -> 0 | F47: =SUMIFS(MOVIMENTO!E155:E363,MOVIMENTO!B155:B363,#REF!,MOVIMENTO!D155:D363,F45) -> 0 | G47: =(G46+C47)-(D47+E47-F47) -> 378
B48: 45901 | C48: =SUMIFS(MOVIMENTO!E364:E421,MOVIMENTO!B364:B421,B44,MOVIMENTO!D364:D421,C45) -> 0 | D48: =SUMIFS(MOVIMENTO!E364:E421,MOVIMENTO!B364:B421,B44,MOVIMENTO!D364:D421,D45) -> 6 | E48: =SUMIFS(MOVIMENTO!E364:E421,MOVIMENTO!B364:B421,B44,MOVIMENTO!D364:D421,E45) -> 0 | F48: =SUMIFS(MOVIMENTO!E364:E421,MOVIMENTO!B364:B421,B44,MOVIMENTO!D364:D421,F45) -> 0 | G48: =(G47+C48)-(D48+E48-F48) -> 372

Sheet CONTAGEM
B1: digitar SOMENTE a coluna "DT CONTAGEM FÍSICA" e "CONTAGEM FÍSICA"
B2: CÓD. | C2: DESCRIÇÃO | D2: SALDO MÊS | E2: DT CONTAGEM FÍSICA | F2: CONTAGEM FÍSICA | G2: DIFERENÇA | H2: DESVIO % | I2: ACURACIDADE % | J2: AJUSTES | K2: DIFERENÇA | M2: 2470 | N2: 2550 | O2: 2731 | P2: 2959 | Q2: 2953
B3: 2470 | C3: CAMISA CHAMPIONS | D3: 417 | E3: 45931 | F3: =756+300 -> 1056 | G3: =D3-F3 -> -639 | H3: =ABS(G3/D3) -> 1.5323741 | I3: =1-(H3) -> -0.5323741 | L3: 10 | M3: 1056 | N3: 63 | O3: 41 | P3: 47 | Q3: 132
B4: 2550 | C4: BONÉ LUXO | D4: 80 | F4: 63 | G4: =D4-F4 -> 17 | H4: =ABS(G4/D4) -> 0.2125 | I4: =1-(H4) -> 0.7875 | L4: 9 | M4: 1073 | N4: 71 | O4: 32 | P4: 47 | Q4: 132
B5: 2731 | C5: BONÉ BRIM | D5: 11 | F5: 41 | G5: =D5-F5 -> -30 | H5: =ABS(G5/D5) -> 2.7272727 | I5: =1-(H5) -> -1.7272727 | L5: 8 | M5: - | N5: 70 | O5: 36 | P5: 47 | Q5: 132
B6: 2959 | C6: CANECA PORTO | D6: 48 | F6: 47 | G6: =D6-F6 -> 1 | H6: =ABS(G6/D6) -> 0.020833333 | I6: =1-(H6) -> 0.97916667 | L6: 7 | M6: - | N6: 83 | O6: 38 | P6: 48 | Q6: 138
B7: 2953 | C7: COPO 500 ML | D7: 137 | F7: 132 | G7: =D7-F7 -> 5 | H7: =ABS(G7/D7) -> 0.03649635 | I7: =1-(H7) -> 0.96350365
B8: 2946 | C8: MASCOTE PORTO | D8: 265 | F8: 258 | G8: =D8-F8 -> 7 | H8: =ABS(G8/D8) -> 0.026415094 | I8: =1-(H8) -> 0.97358491 | M8: 2946 | N8: 3006 | O8: 3007 | P8: 3008 | Q8: 3009
B9: 3006 | C9: REGATA BASQUETE | D9: 51 | F9: 28 | G9: =D9-F9 -> 23 | H9: =ABS(G9/D9) -> 0.45098039 | I9: =1-(H9) -> 0.54901961 | L9: 10 | M9: 258 | N9: 28 | O9: - | P9: 3 | Q9: -
B10: 3007 | C10: CAMISA POLO | L10: 9 | M10: - | N10: 26 | O10: 28 | P10: 3 | Q10: 29
B11: 3008 | C11: CAMISA OFICIAL | D11: 6 | F11: 3 | G11: =D11-F11 -> 3 | H11: =ABS(G11/D11) -> 0.5 | I11: =1-(H11) -> 0.5 | L11: 8 | M11: - | N11: 36 | O11: 29 | P11: 11 | Q11: 27
B12: 3009 | C12: BERMUDA | L12: 7 | M12: - | N12: 58 | O12: 62 | P12: 31 | Q12: 30
B13: 3010 | C13: JAQUETA | D13: 6 | F13: 4 | G13: =D13-F13 -> 2 | H13: =ABS(G13/D13) -> 0.33333333 | I13: =1-(H13) -> 0.66666667
B14: 3049 | C14: CAMISA RETRÔ | D14: 356 | F14: 297 | G14: =D14-F14 -> 59 | H14: =ABS(G14/D14) -> 0.16573034 | I14: =1-(H14) -> 0.83426966 | M14: 3010 | N14: 3049
B15: 2470 | C15: CAMISA CHAMPIONS | D15: 417 | E15: 45901 | F15: =796+277 -> 1073 | G15: =D15-F15 -> -656 | H15: =ABS(G15/D15) -> 1.5731415 | I15: =1-H15 -> -0.57314149 | L15: 10 | M15: 4 | N15: 297
B16: 2550 | C16: BONÉ LUXO | D16: 80 | F16: 71 | G16: =D16-F16 -> 9 | H16: =ABS(G16/D16) -> 0.1125 | I16: =1-H16 -> 0.8875 | L16: 9 | M16: 3 | N16: 307
B17: 2731 | C17: BONÉ BRIM | D17: 11 | F17: 32 | G17: =D17-F17 -> -21 | H17: =ABS(G17/D17) -> 1.9090909 | I17: =1-H17 -> -0.90909091 | L17: 8 | M17: 4 | N17: 366
B18: 2959 | C18: CANECA PORTO | D18: 48 | F18: 47 | G18: =D18-F18 -> 1 | H18: =ABS(G18/D18) -> 0.020833333 | I18: =1-H18 -> 0.97916667 | L18: 7 | M18: 21 | N18: -
B19: 2953 | C19: COPO 500 ML | D19: 137 | F19: 132 | G19: =D19-F19 -> 5 | H19: =ABS(G19/D19) -> 0.03649635 | I19: =1-H19 -> 0.96350365
B20: 2946 | C20: MASCOTE PORTO
B21: 3006 | C21: REGATA BASQUETE | D21: 51 | F21: 26 | G21: =D21-F21 -> 25 | H21: =ABS(G21/D21) -> 0.49019608 | I21: =1-H21 -> 0.50980392
B22: 3007 | C22: CAMISA POLO | D22: 37 | F22: 28 | G22: =D22-F22 -> 9 | H22: =ABS(G22/D22) -> 0.24324324 | I22: =1-H22 -> 0.75675676
B23: 3008 | C23: CAMISA OFICIAL | D23: 6 | F23: 3 | G23: =D23-F23 -> 3 | H23: =ABS(G23/D23) -> 0.5 | I23: =1-H23 -> 0.5
B24: 3009 | C24: BERMUDA | D24: 30 | F24: 29 | G24: =D24-F24 -> 1 | H24: =ABS(G24/D24) -> 0.033333333 | I24: =1-H24 -> 0.96666667
B25: 3010 | C25: JAQUETA | D25: 6 | F25: 3 | G25: =D25-F25 -> 3 | H25: =ABS(G25/D25) -> 0.5 | I25: =1-H25 -> 0.5
B26: 3049 | C26: CAMISA RETRÔ | D26: 356 | F26: 307 | G26: =D26-F26 -> 49 | H26: =ABS(G26/D26) -> 0.13764045 | I26: =1-H26 -> 0.86235955
B27: 2470 | C27: CAMISA CHAMPIONS | E27: 45870
B28: 2550 | C28: BONÉ LUXO | D28: 83 | F28: 70 | G28: =D28-F28 -> 13
B29: 2731 | C29: BONÉ BRIM | D29: 11 | F29: 36 | G29: =D29-F29 -> -25
B30: 2959 | C30: CANECA PORTO | D30: 48 | F30: 47 | G30: =D30-F30 -> 1
B31: 2953 | C31: COPO 500 ML | D31: 137 | F31: 132 | G31: =D31-F31 -> 5
B32: 2946 | C32: MASCOTE PORTO
B33: 3006 | C33: REGATA BASQUETE | D33: 51 | F33: 36 | G33: =D33-F33 -> 15
B34: 3007 | C34: CAMISA POLO | D34: 38 | F34: 29 | G34: =D34-F34 -> 9
B35: 3008 | C35: CAMISA OFICIAL | D35: 6 | F35: 11 | G35: =D35-F35 -> -5
B36: 3009 | C36: BERMUDA | D36: 30 | F36: 27 | G36: =D36-F36 -> 3
B37: 3010 | C37: JAQUETA | D37: 6 | F37: 4 | G37: =D37-F37 -> 2
B38: 3049 | C38: CAMISA RETRÔ | D38: 362 | F38: 366 | G38: =D38-F38 -> -4
B39: 2470 | C39: CAMISA CHAMPIONS | E39: 45839
B40: 2550 | C40: BONÉ LUXO | D40: 93 | F40: 83 | G40: =D40-F40 -> 10
B41: 2731 | C41: BONÉ BRIM | D41: 11 | F41: 38 | G41: =D41-F41 -> -27
B42: 2959 | C42: CANECA PORTO | D42: 48 | F42: 48 | G42: =D42-F42 -> 0
B43: 2953 | C43: COPO 500 ML | D43: 140 | F43: 138 | G43: =D43-F43 -> 2
B44: 2946 | C44: MASCOTE PORTO
B45: 3006 | C45: REGATA BASQUETE | D45: 58 | F45: 58 | G45: =D45-F45 -> 0
B46: 3007 | C46: CAMISA POLO | D46: 38 | F46: 62 | G46: =D46-F46 -> -24
B47: 3008 | C47: CAMISA OFICIAL | D47: 12 | F47: 31 | G47: =D47-F47 -> -19
B48: 3009 | C48: BERMUDA | D48: 30 | F48: 30 | G48: =D48-F48 -> 0
B49: 3010 | C49: JAQUETA | D49: 7 | F49: 21 | G49: =D49-F49 -> -14
B50: 3049 | C50: CAMISA RETRÔ

Sheet RELATÓRIO
B1: Não teve contagem ou contagem totalmente desproporcional
A3: Contagem de Estoque
A4: CÓD. | B4: DESCRIÇÃO | C4: SALDO MÊS | D4: DT CONTAGEM FÍSICA | E4: COMPETÊNCIA | F4: CONTAGEM FÍSICA | G4: DIFERENÇA
A5: 2470 | B5: CAMISA CHAMPIONS | C5: 417 | D5: 45931 | E5: SETEMBRO | F5: =756+300 -> 1056 | G5: =C5-F5 -> -639
A6: 2550 | B6: BONÉ LUXO | C6: 80 | F6: 63 | G6: =C6-F6 -> 17
A7: 2731 | B7: BONÉ BRIM | C7: 11 | F7: 41 | G7: =C7-F7 -> -30 | H7: *Aumento de quantidade física sem ter nota fiscal de compra
A8: 2959 | B8: CANECA PORTO | C8: 48 | F8: 47 | G8: =C8-F8 -> 1
A9: 2953 | B9: COPO 500 ML | C9: 137 | F9: 132 | G9: =C9-F9 -> 5
A10: 2946 | B10: MASCOTE PORTO | C10: 265 | F10: 258 | G10: =C10-F10 -> 7
A11: 3006 | B11: REGATA BASQUETE | C11: 51 | F11: 28 | G11: =C11-F11 -> 23 | H11: *Aumento de quantidade física sem ter nota fiscal de compra
A12: 3007 | B12: CAMISA POLO
A13: 3008 | B13: CAMISA OFICIAL | C13: 6 | F13: 3 | G13: =C13-F13 -> 3
A14: 3009 | B14: BERMUDA
A15: 3010 | B15: JAQUETA | C15: 6 | F15: 4 | G15: =C15-F15 -> 2 | H15: *Aumento de quantidade física sem ter nota fiscal de compra
A16: 3049 | B16: CAMISA RETRÔ | C16: 356 | F16: 297 | G16: =C16-F16 -> 59
A17: 2470 | B17: CAMISA CHAMPIONS | C17: 417 | D17: 45901 | E17: AGOSTO | F17: =796+277 -> 1073 | G17: =C17-F17 -> -656
A18: 2550 | B18: BONÉ LUXO | C18: 80 | F18: 71 | G18: =C18-F18 -> 9
A19: 2731 | B19: BONÉ BRIM | C19: 11 | F19: 32 | G19: =C19-F19 -> -21
A20: 2959 | B20: CANECA PORTO | C20: 48 | F20: 47 | G20: =C20-F20 -> 1
A21: 2953 | B21: COPO 500 ML | C21: 137 | F21: 132 | G21: =C21-F21 -> 5
A22: 2946 | B22: MASCOTE PORTO
A23: 3006 | B23: REGATA BASQUETE | C23: 51 | F23: 26 | G23: =C23-F23 -> 25
A24: 3007 | B24: CAMISA POLO | C24: 37 | F24: 28 | G24: =C24-F24 -> 9
A25: 3008 | B25: CAMISA OFICIAL | C25: 6 | F25: 3 | G25: =C25-F25 -> 3
A26: 3009 | B26: BERMUDA | C26: 30 | F26: 29 | G26: =C26-F26 -> 1 | H26: *Aumento de quantidade física sem ter nota fiscal de compra
A27: 3010 | B27: JAQUETA | C27: 6 | F27: 3 | G27: =C27-F27 -> 3
A28: 3049 | B28: CAMISA RETRÔ | C28: 356 | F28: 307 | G28: =C28-F28 -> 49
A29: 2470 | B29: CAMISA CHAMPIONS | D29: 45870 | E29: JULHO
A30: 2550 | B30: BONÉ LUXO | C30: 83 | F30: 70 | G30: =C30-F30 -> 13
A31: 2731 | B31: BONÉ BRIM | C31: 11 | F31: 36 | G31: =C31-F31 -> -25
A32: 2959 | B32: CANECA PORTO | C32: 48 | F32: 47 | G32: =C32-F32 -> 1
A33: 2953 | B33: COPO 500 ML | C33: 137 | F33: 132 | G33: =C33-F33 -> 5
A34: 2946 | B34: MASCOTE PORTO
A35: 3006 | B35: REGATA BASQUETE | C35: 51 | F35: 36 | G35: =C35-F35 -> 15
A36: 3007 | B36: CAMISA POLO | C36: 38 | F36: 29 | G36: =C36-F36 -> 9
A37: 3008 | B37: CAMISA OFICIAL | C37: 6 | F37: 11 | G37: =C37-F37 -> -5
A38: 3009 | B38: BERMUDA | C38: 30 | F38: 27 | G38: =C38-F38 -> 3
A39: 3010 | B39: JAQUETA | C39: 6 | F39: 4 | G39: =C39-F39 -> 2
A40: 3049 | B40: CAMISA RETRÔ | C40: 362 | F40: 366 | G40: =C40-F40 -> -4
A41: 2470 | B41: CAMISA CHAMPIONS | D41: 45839 | E41: JUNHO
A42: 2550 | B42: BONÉ LUXO | C42: 93 | F42: 83 | G42: =C42-F42 -> 10
A43: 2731 | B43: BONÉ BRIM | C43: 11 | F43: 38 | G43: =C43-F43 -> -27
A44: 2959 | B44: CANECA PORTO | C44: 48 | F44: 48 | G44: =C44-F44 -> 0
A45: 2953 | B45: COPO 500 ML | C45: 140 | F45: 138 | G45: =C45-F45 -> 2
A46: 2946 | B46: MASCOTE PORTO
A47: 3006 | B47: REGATA BASQUETE | C47: 58 | F47: 58 | G47: =C47-F47 -> 0
A48: 3007 | B48: CAMISA POLO | C48: 38 | F48: 62 | G48: =C48-F48 -> -24
A49: 3008 | B49: CAMISA OFICIAL | C49: 12 | F49: 31 | G49: =C49-F49 -> -19
A50: 3009 | B50: BERMUDA | C50: 30 | F50: 30 | G50: =C50-F50 -> 0
A51: 3010 | B51: JAQUETA | C51: 7 | F51: 21 | G51: =C51-F51 -> -14
A52: 3049 | B52: CAMISA RETRÔ

Sheet RELATÓRIO VENDAS
B1: Ano de 2025
C3: CHAMPIONS | E3: BONÉ LUXO | G3: BONÉ BRIM | I3: CANECA | K3: COPO | M3: MASCOTE | O3: REGATA | Q3: CAMISA POLO | S3: CAMISA OFICIAL | U3: BERMUDA | W3: JAQUETA | Y3: CAMISA RETRÔ
C4: QTD | D4: VLR | E4: QTD | F4: VLR | G4: QTD | H4: VLR | I4: QTD | J4: VLR | K4: QTD | L4: VLR | M4: QTD | N4: VLR | O4: QTD | P4: VLR | Q4: QTD | R4: VLR | S4: QTD | T4: VLR | U4: QTD | V4: VLR | W4: QTD | X4: VLR | Y4: QTD | Z4: VLR
B5: Janeiro | C5: 86 | D5: 14920 | E5: 13 | F5: 760 | G5: 5 | H5: 300 | I5: 0 | J5: 0 | K5: 2 | L5: 300 | M5: 0 | N5: 0 | O5: - | P5: - | Q5: - | R5: - | S5: - | T5: - | U5: - | V5: - | W5: - | X5: - | Y5: - | Z5: -
B6: Fevereiro | C6: 78 | D6: 13080 | E6: 13 | F6: 770 | G6: 1 | H6: 60 | I6: 1 | J6: 50 | K6: 1 | L6: 150 | M6: 1 | N6: 100 | O6: - | P6: - | Q6: - | R6: - | S6: - | T6: - | U6: - | V6: - | W6: - | X6: - | Y6: - | Z6: -
B7: Março | C7: 98 | D7: 16630 | E7: 8 | F7: 480 | G7: 4 | H7: 240 | I7: 0 | J7: 0 | K7: 0 | L7: 0 | M7: 3 | N7: 300 | O7: - | P7: - | Q7: - | R7: - | S7: - | T7: - | U7: - | V7: - | W7: - | X7: - | Y7: - | Z7: -
B8: Abril | C8: 127 | D8: 21400 | E8: 12 | F8: 720 | G8: 3 | H8: 170 | I8: 1 | J8: 50 | K8: 0 | L8: 0 | M8: 3 | N8: 260 | O8: 0 | P8: 0 | Q8: 0 | R8: 0 | S8: 0 | T8: 0 | U8: 0 | V8: 0 | W8: 0 | X8: 0 | Y8: - | Z8: -
B9: Maio | C9: 106 | D9: 18860 | E9: 24 | F9: 1440 | G9: 0 | H9: 0 | I9: 0 | J9: 0 | K9: 3 | L9: 450 | M9: 4 | N9: 360 | O9: 0 | P9: 0 | Q9: 0 | R9: 0 | S9: 0 | T9: 0 | U9: 0 | V9: 0 | W9: 0 | X9: 0 | Y9: - | Z9: -
B10: Junho | C10: 34 | D10: 5820 | E10: 4 | F10: 240 | G10: 0 | H10: 0 | I10: 0 | J10: 0 | K10: 0 | L10: 0 | M10: 1 | N10: 100 | O10: 0 | P10: 0 | Q10: 0 | R10: 0 | S10: 0 | T10: 0 | U10: 0 | V10: 0 | W10: 0 | X10: 0 | Y10: - | Z10: -
B11: Julho | C11: 178 | D11: 25282 | E11: 14 | F11: 816 | G11: 1 | H11: 60 | I11: 0 | J11: 0 | K11: 0 | L11: 0 | M11: 1 | N11: 100 | O11: 2 | P11: 340 | Q11: 2 | R11: 360 | S11: 8 | T11: 1462 | U11: 0 | V11: 0 | W11: 8 | X11: 1850 | Y11: 22 | Z11: 3960
B12: Agosto | C12: =199-6-2-3 -> 188 | D12: 26829 | E12: 11 | F12: 600 | G12: 0 | H12: 0 | I12: 0 | J12: 0 | K12: 3 | L12: 450 | M12: 7 | N12: 500 | O12: 7 | P12: 1088 | Q12: 0 | R12: 0 | S12: 6 | T12: 1075 | U12: 0 | V12: 0 | W12: 0 | X12: 0 | Y12: 15 | Z12: 2592
B13: Setembro | C13: 41 | D13: 6408 | E13: 3 | F13: 168 | G13: 0 | H13: 0 | I13: 0 | J13: 0 | K13: 0 | L13: 0 | M13: 0 | N13: 0 | O13: 0 | P13: 0 | Q13: 1 | R13: 200 | S13: 0 | T13: 0 | U13: 0 | V13: 0 | W13: 0 | X13: 0 | Y13: 6 | Z13: 1080
B15: Saldo total por produto até setembro/2025 | H15: Saldo total por mês até setembro/2025
B17: PRODUTO | D17: QTD | E17: VALOR | H17: MÊS | J17: QTD | K17: VALOR
B18: CHAMPIONS | D18: =SUM(C5:C13) -> 936 | E18: =SUM(D5:D13) -> 149229 | H18: JANEIRO | J18: =SUM(C5+E5+G5+I5+K5+M5) -> 106 | K18: =SUM(D5+F5+H5+J5+L5+N5) -> 16280
B19: BONÉ LUXO | D19: =SUM(E5:E13) -> 102 | E19: =SUM(F5:F13) -> 5994 | H19: FEVEREIRO | J19: =SUM(C6+E6+G6+I6+K6+M6) -> 95 | K19: =SUM(D6+F6+H6+J6+L6+N6) -> 14210
B20: BONÉ BRIM | D20: =SUM(G5:G13) -> 14 | E20: =SUM(H5:H13) -> 830 | H20: MARÇO | J20: =SUM(C7+E7+G7+I7+K7+M7) -> 113 | K20: =SUM(D7+F7+H7+J7+L7+N7) -> 17650
B21: CANECA | D21: =SUM(I5:I13) -> 2 | E21: =SUM(J5:J13) -> 100 | H21: ABRIL | J21: =SUM(C8+E8+G8+I8+K8+M8+O8+Q8+S8+U8+W8) -> 146 | K21: =SUM(D8+F8+H8+J8+L8+N8+P8+R8+T8+V8+X8) -> 22600
B22: COPO | D22: =SUM(K5:K13) -> 9 | E22: =SUM(L5:L13) -> 1350 | H22: MAIO | J22: =SUM(C9+E9+G9+I9+K9+M9+O9+Q9+S9+U9+W9) -> 137 | K22: =SUM(D9+F9+H9+J9+L9+N9+P9+R9+T9+V9+X9) -> 21110
B23: MASCOTE | D23: =SUM(M5:M13) -> 20 | E23: =SUM(N5:N13) -> 1720 | H23: JUNHO | J23: =SUM(C10+E10+G10+I10+K10+M10+O10+Q10+S10+U10+W10) -> 39 | K23: =SUM(D10+F10+H10+J10+L10+N10+P10+R10+T10+V10+X10) -> 6160
B24: REGATA | D24: =SUM(O8:O13) -> 9 | E24: =SUM(P5:P13) -> 1428 | H24: JULHO | J24: =SUM(C11+E11+G11+I11+K11+M11+O11+Q11+S11+U11+W11+Y11) -> 236 | K24: =SUM(D11+F11+H11+J11+L11+N11+P11+R11+T11+V11+X11+Z11) -> 34230
B25: CAMISA POLO | D25: =SUM(Q8:Q13) -> 3 | E25: =SUM(R8:R13) -> 560 | H25: AGOSTO | J25: =SUM(C12+E12+G12+I12+K12+M12+O12+Q12+S12+U12+W12+Y12) -> 237 | K25: =SUM(D12+F12+H12+J12+L12+N12+P12+R12+T12+V12+X12+Z12) -> 33134
B26: CAMISA OFICIAL | D26: =SUM(S8:S13) -> 14 | E26: =SUM(T8:T13) -> 2537 | H26: SETEMBRO | J26: =SUM(C13+E13+G13+I13+K13+M13+O13+Q13+S13+U13+W13+Y13) -> 51 | K26: =SUM(D13+F13+H13+J13+L13+N13+P13+R13+T13+V13+X13+Z13) -> 7856
B27: BERMUDA | D27: =SUM(U5:U13) -> 0 | E27: =SUM(V8:V13) -> 0
B28: JAQUETA | D28: =SUM(W8:W13) -> 8 | E28: =SUM(X8:X13) -> 1850
B29: CAMISA RETRÔ | D29: =SUM(Y11:Y13) -> 43 | E29: =SUM(Z11:Z13) -> 7632
B31: TOTAL PRODUTOS VENDIDOS ATÉ SETEMBRO/2025 | G31: 1160
B32: TOTAL DOS VALROES ATÉ SETEMBRO/2025 | G32: 173230
B34: * Foi consideras as vendas a partir do dia 15/01 (abertura do quiosque) + vendas externas + vendas para a diretoria
B35: * Para os valores foram considerados vlr bruto - desconto
B36: * Dados não são 100% iguais a realidade pois existem notas fiscais que foram emitidas em atraso / devolvidas / emitidas de forma errônea... apesar dos ajustes realizados, é preciso considerar uma margem de erros para quantidades e valores acima.
B37: * Os valores de cada mês não siginfica que entraram no extrato naquele mesmo mês, pois, vendas por cartão de crédito caem 1 mês após a venda.
B39: ANO DE 2024
C41: CHAMPIONS | E41: BONÉ LUXO | G41: BONÉ BRIM | J41: Saldo Total por produto até setembro/2024 | O41: Saldo total por mês até setembro/2024
C42: QTD | D42: VLR | E42: QTD | F42: VLR | G42: QTD | H42: VLR
B43: Janeiro | C43: 19 | D43: 1900 | E43: 1 | F43: 50 | G43: 0 | H43: 0 | J43: PRODUTO | L43: QTD | M43: VALOR | O43: MÊS | Q43: QTD | R43: VALOR
B44: Fevereiro | C44: 69 | D44: 6900 | E44: 15 | F44: 700 | G44: 0 | H44: 0 | J44: CHAMPIONS | L44: =SUM(C43:C51) -> 479 | M44: =SUM(D43:D51) -> 51598.85 | O44: JANEIRO | Q44: =SUM(C43+E43+G43) -> 20 | R44: =SUM(D43+F43+H43) -> 1950
B45: Março | C45: 35 | D45: 3420 | E45: 3 | F45: 110 | G45: 1 | H45: 50 | J45: BONÉ LUXO | L45: =SUM(E43:E51) -> 112 | M45: =SUM(F43:F51) -> 5395 | O45: FEVEREIRO | Q45: =SUM(C44+E44+G44) -> 84 | R45: =SUM(D44+F44+H44) -> 7600
B46: Abril | C46: 34 | D46: 3400 | E46: 0 | F46: 0 | G46: 0 | H46: 0 | J46: BONÉ BRIM | L46: =SUM(G43:G51) -> 20 | M46: =SUM(H43:H51) -> 905 | O46: MARÇO | Q46: =SUM(C45+E45+G45) -> 39 | R46: =SUM(D45+F45+H45) -> 3580
B47: Maio | C47: 31 | D47: 3100 | E47: 0 | F47: 0 | G47: 0 | H47: 0 | O47: ABRIL | Q47: =SUM(C46+E46+G46) -> 34 | R47: =SUM(D46+F46+H46) -> 3400
B48: Junho | C48: 56 | D48: 5524.43 | E48: 44 | F48: 2150 | G48: 18 | H48: 810 | O48: MAIO | Q48: =SUM(C47+E47+G47) -> 31 | R48: =SUM(D47+F47+H47) -> 3100
B49: Julho | C49: 23 | D49: 2259.42 | E49: 13 | F49: 625 | G49: 1 | H49: 45 | O49: JUNHO | Q49: =SUM(C48+E48+G48) -> 118 | R49: =SUM(D48+F48+H48) -> 8484.43
B50: Agosto | C50: 169 | D50: 19655 | E50: 26 | F50: 1260 | G50: 0 | H50: 0 | O50: JULHO | Q50: =SUM(C49+E49+G49) -> 37 | R50: =SUM(D49+F49+H49) -> 2929.42
B51: Setembro | C51: 43 | D51: 5440 | E51: 10 | F51: 500 | G51: 0 | H51: 0 | O51: AGOSTO | Q51: =SUM(C50+E50+G50) -> 195 | R51: =SUM(D50+F50+H50) -> 20915
O52: SETEMBRO | Q52: =SUM(C51+E51+G51) -> 53 | R52: =SUM(D51+F51+H51) -> 5940
B54: TOTAL PRODUTOS VENDIDOS ATÉ SETEMBRO/2024 | G54: 611
B55: TOTAL DOS VALROES ATÉ SETEMBRO/2024 | G55: 57898.85
B58: * Foi considera as vendas na prórpria Porto vitória (neste ano ainda não tinha o quiosque) + vendas externas + vendas para a diretoria
B59: * Para os valores foram considerados vlr bruto - desconto
B60: * Dados não são 100% iguais a realidade pois existem notas fiscais que foram emitidas em atraso / devolvidas / emitidas de forma errônea... apesar dos ajustes realizados, é preciso considerar uma margem de erros para quantidades e valores acima.
B61: * Os valores de cada mês não siginfica que entraram no extrato naquele mesmo mês, pois, vendas por cartão de crédito caem 1 mês após a venda.

Sheet 07.2025
A1: REGISTRO DE INVENTÁRIO
A2: FIRMA: CONTO DE FIDELIDADE DO BRASIL LTDA
A3: INSC. ESTADUAL: 084037180 | C3: CNPJ: 35.515.223/0001-76
A4: FOLHA: 2 | C4: ESTOQUE EXISTENTES EM: 31/07/2025
A5: CLASSIFICAÇÃO FISCAL | B5: DISCRIMINAÇÃO | C5: UNIDADE | D5: QUANTIDADE | E5: VALORES
E6: UNITÁRIO | F6: TOTAL
A7: 61.05.20.00 | B7: CAMISA CHAMPIONS | C7: UN. | D7: =886-123-106-34-178 -> 445 | E7: 87.92 | F7: =E7*D7 -> 39124.4
A8: 61.05.20.00 | B8: CAMISA CHAMPIONS | C8: UN. | D8: 200 | E8: 109.9 | F8: =E8*D8 -> 21980
A9: 65.05.00.11 | B9: BONÉ LUXO | C9: UN. | D9: 93 | E9: 29 | F9: =E9*D9 -> 2697
A10: 65.05.00.11 | B10: BONÉ BRIM | C10: UN. | D10: 11 | E10: 29 | F10: =E10*D10 -> 319
A11: 49.08.90.00 | B11: ETQ. LETRA PRINT FIX | C11: UN. | D11: 6046 | E11: 0.57 | F11: =E11*D11 -> 3446.22
A12: 49.08.90.00 | B12: ETQ. NÚMERO PRINT FIX | C12: UN. | D12: 1208 | E12: 4.28 | F12: =E12*D12 -> 5170.24
A13: 95.03.00.31 | B13: MASCOTE PORTO VITÓRIA | C13: UN. | D13: 273 | E13: 62.5 | F13: =E13*D13 -> 17062.5
A14: 96.17.00.10 | B14: COPO TÉRMICO TULIP 500ML | C14: UN. | D14: 140 | E14: 150 | F14: =E14*D14 -> 21000
A15: 96.17.00.10 | B15: GARRAFA TÉRMICA 660 ML | C15: UN. | D15: 1 | E15: 180 | F15: =E15*D15 -> 180
A16: 69.12.00.00 | B16: CANECA PORTO VITÓRIA | C16: UN. | D16: 48 | E16: 15 | F16: =E16*D16 -> 720
A17: 61.05.20.00 | B17: REGATA BASQUETE ESPECIAL TORCEDOR | C17: UN. | D17: 58 | E17: 79.92 | F17: =E17*D17 -> 4635.36
A18: 61.05.20.00 | B18: CAMISA POLO TORCEDOR | C18: UN. | D18: 38 | E18: 95.92 | F18: =E18*D18 -> 3644.96
A19: 61.05.20.00 | B19: CAMISA OFICIAL T-SHIRT TORCEDOR | C19: UN. | D19: 12 | E19: 95.92 | F19: =E19*D19 -> 1151.04
... A22: 61.05.20.00 | B22: CAMISA ESPECIAL RETRÔ | C22: UN. | D22: 378 | E22: 129.9 | F22: =E22*D22 -> 49102.2
D24: =SUM(D7:D22) -> 8988 | F24: =SUM(F7:F22) -> 172989.96

Sheet 08.2025
A1: REGISTRO DE INVENTÁRIO
A2: FIRMA: CONTO DE FIDELIDADE DO BRASIL LTDA
A3: INSC. ESTADUAL: 084037180 | C3: CNPJ: 35.515.223/0001-76
A4: FOLHA: 2 | C4: ESTOQUE EXISTENTES EM: 31/08/2025
A5: CLASSIFICAÇÃO FISCAL | B5: DISCRIMINAÇÃO | C5: UNIDADE | D5: QUANTIDADE | E5: VALORES
E6: UNITÁRIO | F6: TOTAL
A7: 61.05.20.00 | B7: CAMISA CHAMPIONS | C7: UN. | D7: =886-123-106-34-178-187 -> 258 | E7: 87.92 | F7: =E7*D7 -> 22683.36
A8: 61.05.20.00 | B8: CAMISA CHAMPIONS | C8: UN. | D8: 200 | E8: 109.9 | F8: =E8*D8 -> 21980
A9: 65.05.00.11 | B9: BONÉ LUXO | C9: UN. | D9: 83 | E9: 29 | F9: =E9*D9 -> 2407
A10: 65.05.00.11 | B10: BONÉ BRIM | C10: UN. | D10: 11 | E10: 29 | F10: =E10*D10 -> 319
A11: 49.08.90.00 | B11: ETQ. LETRA PRINT FIX | C11: UN. | D11: 6046 | E11: 0.57 | F11: =E11*D11 -> 3446.22
A12: 49.08.90.00 | B12: ETQ. NÚMERO PRINT FIX | C12: UN. | D12: 1208 | E12: 4.28 | F12: =E12*D12 -> 5170.24
A13: 95.03.00.31 | B13: MASCOTE PORTO VITÓRIA | C13: UN. | D13: 265 | E13: 62.5 | F13: =E13*D13 -> 16562.5
A14: 96.17.00.10 | B14: COPO TÉRMICO TULIP 500ML | C14: UN. | D14: 137 | E14: 150 | F14: =E14*D14 -> 20550
A15: 96.17.00.10 | B15: GARRAFA TÉRMICA 660 ML | C15: UN. | D15: 1 | E15: 180 | F15: =E15*D15 -> 180
A16: 69.12.00.00 | B16: CANECA PORTO VITÓRIA | C16: UN. | D16: 48 | E16: 15 | F16: =E16*D16 -> 720
A17: 61.05.20.00 | B17: REGATA BASQUETE ESPECIAL TORCEDOR | C17: UN. | D17: 51 | E17: 79.92 | F17: =E17*D17 -> 4075.92
A18: 61.05.20.00 | B18: CAMISA POLO TORCEDOR | C18: UN. | D18: 38 | E18: 95.92 | F18: =E18*D18 -> 3644.96
A19: 61.05.20.00 | B19: CAMISA OFICIAL T-SHIRT TORCEDOR | C19: UN. | D19: 6 | E19: 95.92 | F19: =E19*D19 -> 575.52
... A22: 61.05.20.00 | B22: CAMISA ESPECIAL RETRÔ | C22: UN. | D22: 378 | E22: 129.9 | F22: =E22*D22 -> 49102.2
D24: =SUM(D7:D22) -> 8766 | F24: =SUM(F7:F22) -> 154054.04

Sheet 09.2025
A1: REGISTRO DE INVENTÁRIO
A2: FIRMA: CONTO DE FIDELIDADE DO BRASIL LTDA
A3: INSC. ESTADUAL: 084037180 | C3: CNPJ: 35.515.223/0001-76
A4: FOLHA: 2 | C4: ESTOQUE EXISTENTES EM: 30/09/2025
A5: CLASSIFICAÇÃO FISCAL | B5: DISCRIMINAÇÃO | C5: UNIDADE | D5: QUANTIDADE | E5: VALORES
E6: UNITÁRIO | F6: TOTAL
A7: 61.05.20.00 | B7: CAMISA CHAMPIONS | C7: UN. | D7: =886-123-106-34-178-187-36 -> 222 | E7: 87.92 | F7: =E7*D7 -> 19518.24
A8: 61.05.20.00 | B8: CAMISA CHAMPIONS | C8: UN. | D8: 200 | E8: 109.9 | F8: =E8*D8 -> 21980
A9: 65.05.00.11 | B9: BONÉ LUXO | C9: UN. | D9: 80 | E9: 29 | F9: =E9*D9 -> 2320
A10: 65.05.00.11 | B10: BONÉ BRIM | C10: UN. | D10: 11 | E10: 29 | F10: =E10*D10 -> 319
A11: 49.08.90.00 | B11: ETQ. LETRA PRINT FIX | C11: UN. | D11: 6046 | E11: 0.57 | F11: =E11*D11 -> 3446.22
A12: 49.08.90.00 | B12: ETQ. NÚMERO PRINT FIX | C12: UN. | D12: 1208 | E12: 4.28 | F12: =E12*D12 -> 5170.24
A13: 95.03.00.31 | B13: MASCOTE PORTO VITÓRIA | C13: UN. | D13: 265 | E13: 62.5 | F13: =E13*D13 -> 16562.5
A14: 96.17.00.10 | B14: COPO TÉRMICO TULIP 500ML | C14: UN. | D14: 137 | E14: 150 | F14: =E14*D14 -> 20550
A15: 96.17.00.10 | B15: GARRAFA TÉRMICA 660 ML | C15: UN. | D15: 1 | E15: 180 | F15: =E15*D15 -> 180
A16: 69.12.00.00 | B16: CANECA PORTO VITÓRIA | C16: UN. | D16: 48 | E16: 15 | F16: =E16*D16 -> 720
A17: 61.05.20.00 | B17: REGATA BASQUETE ESPECIAL TORCEDOR | C17: UN. | D17: 51 | E17: 79.92 | F17: =E17*D17 -> 4075.92
A18: 61.05.20.00 | B18: CAMISA POLO TORCEDOR | C18: UN. | D18: 37 | E18: 95.92 | F18: =E18*D18 -> 3549.04
A19: 61.05.20.00 | B19: CAMISA OFICIAL T-SHIRT TORCEDOR | C19: UN. | D19: 6 | E19: 95.92 | F19: =E19*D19 -> 575.52
... A22: 61.05.20.00 | B22: CAMISA ESPECIAL RETRÔ | C22: UN. | D22: 372 | E22: 129.9 | F22: =E22*D22 -> 48322.8
D24: =SUM(D7:D22) -> 8720 | F24: =SUM(F7:F22) -> 149926.6
